Workbook

Sheet Start_Here
B1: Wattlebird Support Services: Practice Pack
B2: PVA Academy | NDIS Virtual Assistant Foundations | FICTIONAL DATA ONLY
B4: Wattlebird 'today' (simulation date) | C4: 46328 | D4: The practice week starts on this Monday. Formulas use it instead of today's real date. Please don't change it.
B5: Screening reminder window (days) | C5: 60 | D5: Wattlebird's own fictional rule: flag screening checks expiring within this many days.
B7: Colour legend
B8: Staff records in this pack | C8: 22 | D8: Corrected: 21 fictional staff records are included.
B9: Teal header row | C9: Column names
B10: Pack version | C10: v2.3.7 learner bundle | D10: M15 rebuild: rebuilt capstone inputs, concrete trial records, source/navigation repairs, assessment integrity fixes.
B11: Plain cells with formulas | C11: Calculated for you
B12: Unified workflow | C12: DO → CHECK → CLASSIFY → ACT/HAND OFF → FOLLOW UP → CLOSE | D12: Classification: OK / FLAG / ASK / ESCALATE
A13: Tab | B13: Start_Here | C13: Practice workbook sheet
A14: Tab | B14: Provider | C14: Fictional provider profile and house rules
A15: Tab | B15: Participants | C15: Fictional participant records and plan context
A16: Tab | B16: Staff | C16: Fictional staff, availability and screening
A17: Tab | B17: Roster | C17: Practice-week scheduling records
A18: Tab | B18: Price_Table | C18: Fictional practice prices and limits
A19: Tab | B19: Invoice_Batch | C19: Fictional invoice batch for M11 practice
A20: Tab | B20: Inbox | C20: Fictional incoming messages and task context
A21: Tab | B21: Task_Board | C21: Fictional task queue
A22: Tab | B22: Incident_Log | C22: Fictional incident records
A23: Tab | B23: Complaints_Log | C23: Fictional complaint records
A24: Tab | B24: Follow_Up_Log | C24: Track unresolved work and closure
... A64: Tab | B64: M15_Capstone_Invoice_Evidence | C64: Neutral assessment evidence for CAP-05

Sheet Provider
A1: About Wattlebird Support Services (fictional)
A2: An invented, mid-sized NDIS provider used for practice. Not a real business.
A3: Topic | B3: Detail
A4: Locations | B4: Melbourne head office and a small Gold Coast site
A5: Time zones this week | B5: Melbourne: AEDT (daylight saving). Gold Coast: AEST (no daylight saving).
A6: Office hours | B6: Melbourne Mon to Fri 8:30 am to 5:00 pm (Melbourne time). Gold Coast Mon to Thu 9:00 am to 4:00 pm (Gold Coast time).
A7: Team (about 25) | B7: Director, operations manager, 2 support coordinators, 1 plan manager, 1 admin officer, about 12 support workers, contracted allied health. The Staff tab lists the people used in this pack.
A8: Participants | B8: About 40 in total. 12 are used in this pack.
A9: Services | B9: Support coordination, plan management, daily living and community participation supports, allied health.
A10: Your role | B10: New part-time virtual assistant reporting to the operations manager (Rhonda Blake). Tasks arrive by email.
A11: Systems | B11: Google Workspace, this Google Sheets pack, a free task board, and free chat. Paid NDIS systems are only shown as mock screens in the course.
A12: Fictional house rule: cancellations | B12: Cancellations with less than 2 business days' notice are recorded. The operations manager decides whether any charge applies.
A13: Fictional house rule: escalation | B13: Anything involving safety, a complaint, a privacy slip, or an urgent incident goes straight to the operations manager, right away. Don't wait for the next day.
A14: Fictional house rule: information | B14: Participant information is only shared with the participant or someone the operations manager confirms has permission.
... A24: Routine handover channel (fictional) | B24: Email to Rhonda Blake / the next responsible contact. Use Wattlebird Urgent Chat for urgent handoffs.

Sheet Participants
A1: Participants (fictional)
A2: 12 invented participants. Remaining funds are invented and approximate (all budgets combined).
A3: ID | B3: Name | C3: Site | D3: Plan management | E3: Main supports | F3: Funded budgets | G3: Plan review date | H3: Service agreement | I3: Approx. remaining funds (AUD)
A4: P01 | B4: Marisol Reyes | C4: Melbourne | D4: Plan-managed | E4: Community access; physiotherapy | F4: Core; Capacity Building | G4: 46456 | H4: Signed | I4: 6200
A5: P02 | B5: Daniel Whitfield | C5: Melbourne | D5: Self-managed | E5: Daily living support | F5: Core | G5: 46407 | H5: Signed | I5: 3100
A6: P03 | B6: Aisha Rahman | C6: Melbourne | D6: NDIA-managed | E6: Support coordination | F6: Capacity Building; Core | G6: 46370 | H6: Signed | I6: 2800
A7: P04 | B7: Tom Nguyen | C7: Melbourne | D7: Plan-managed | E7: Daily living; occupational therapy | F7: Core; Capacity Building | G7: 46512 | H7: Signed | I7: 7400
A8: P05 | B8: Priya Nair | C8: Melbourne | D8: Self-managed | E8: Community participation | F8: Core | G8: 46499 | H8: Signed | I8: 5100
A9: P06 | B9: Jack O'Connor | C9: Melbourne | D9: NDIA-managed | E9: Daily living | F9: Core | G9: 46568 | H9: Signed | I9: 9800
A10: P07 | B10: Lucia Fernandez | C10: Melbourne | D10: Plan-managed | E10: Allied health (psychology) | F10: Capacity Building | G10: 46419 | H10: Due for renewal | I10: 2300
A11: P08 | B11: Ben Taylor | C11: Gold Coast | D11: Plan-managed | E11: Community access | F11: Core | G11: 46464 | H11: Signed | I11: 4600
A12: P09 | B12: Grace Mitchell | C12: Melbourne | D12: To be confirmed | E12: To be confirmed | F12: To be confirmed | H12: Not started
A13: P10 | B13: Samuel Osei | C13: Melbourne | D13: NDIA-managed | E13: Support coordination | F13: Capacity Building | G13: 46395 | H13: Signed | I13: 1900
A14: P11 | B14: Hannah Kowalski | C14: Melbourne | D14: Self-managed | E14: Daily living | F14: Core | G14: 46534 | H14: Signed | I14: 8200
A15: P12 | B15: Ravi Patel | C15: Melbourne | D15: Plan-managed | E15: Allied health (physiotherapy); daily living | F15: Core; Capacity Building | G15: 46444 | H15: Signed | I15: 420

Sheet Staff
A1: Staff (fictional)
A2: Screening reminder and rostered hours are calculated. Reminder window is set on Start_Here. Only authorised staff manage the real screening database.
A3: ID | B3: Name | C3: Role | D3: Role type | E3: Site | F3: Employment | G3: Usual availability | H3: Unavailable from | I3: Unavailable to | J3: Screening check expiry | K3: Screening reminder | L3: Rostered hours this week | M3: Notes
A4: S01 | B4: Callum Reid | C4: Director | D4: Non-direct | E4: Melbourne | F4: Full-time | G4: Mon-Fri | K4: =IF(J4="","",IF(J4<Start_Here!$C$4,"EXPIRED",IF(J4-Start_Here!$C$4<=Start_Here!$C$5,"Expires within reminder window","OK"))) | L4: =SUMIFS(Roster!$F$4:$F$60,Roster!$J$4:$J$60,A4,Roster!$M$4:$M$60,"<>Cancelled") -> 0
A5: S02 | B5: Rhonda Blake | C5: Operations manager | D5: Non-direct | E5: Melbourne | F5: Full-time | G5: Mon-Fri | K5: =IF(J5="","",IF(J5<Start_Here!$C$4,"EXPIRED",IF(J5-Start_Here!$C$4<=Start_Here!$C$5,"Expires within reminder window","OK"))) | L5: =SUMIFS(Roster!$F$4:$F$60,Roster!$J$4:$J$60,A5,Roster!$M$4:$M$60,"<>Cancelled") -> 0 | M5: Learner's manager
A6: S03 | B6: Tessa Nguyen | C6: Support coordinator | D6: Non-direct | E6: Melbourne | F6: Full-time | G6: Mon-Fri | K6: =IF(J6="","",IF(J6<Start_Here!$C$4,"EXPIRED",IF(J6-Start_Here!$C$4<=Start_Here!$C$5,"Expires within reminder window","OK"))) | L6: =SUMIFS(Roster!$F$4:$F$60,Roster!$J$4:$J$60,A6,Roster!$M$4:$M$60,"<>Cancelled") -> 0
A7: S04 | B7: Marcus Feld | C7: Support coordinator | D7: Non-direct | E7: Gold Coast | F7: Part-time | G7: Mon-Thu | J7: 46568 | K7: =IF(J7="","",IF(J7<Start_Here!$C$4,"EXPIRED",IF(J7-Start_Here!$C$4<=Start_Here!$C$5,"Expires within reminder window","OK"))) -> OK | L7: =SUMIFS(Roster!$F$4:$F$60,Roster!$J$4:$J$60,A7,Roster!$M$4:$M$60,"<>Cancelled") -> 0
A8: S05 | B8: Olivia Grant | C8: Plan manager | D8: Non-direct | E8: Melbourne | F8: Full-time | G8: Mon-Fri | K8: =IF(J8="","",IF(J8<Start_Here!$C$4,"EXPIRED",IF(J8-Start_Here!$C$4<=Start_Here!$C$5,"Expires within reminder window","OK"))) | L8: =SUMIFS(Roster!$F$4:$F$60,Roster!$J$4:$J$60,A8,Roster!$M$4:$M$60,"<>Cancelled") -> 0
A9: S06 | B9: Jamal Ortiz | C9: Admin officer | D9: Non-direct | E9: Melbourne | F9: Part-time | G9: Mon-Thu | K9: =IF(J9="","",IF(J9<Start_Here!$C$4,"EXPIRED",IF(J9-Start_Here!$C$4<=Start_Here!$C$5,"Expires within reminder window","OK"))) | L9: =SUMIFS(Roster!$F$4:$F$60,Roster!$J$4:$J$60,A9,Roster!$M$4:$M$60,"<>Cancelled") -> 0
A10: W01 | B10: Joy Villanueva | C10: Support worker | D10: Direct support | E10: Melbourne | F10: Part-time | G10: Mon, Tue, Thu, Fri | J10: 46827 | K10: =IF(J10="","",IF(J10<Start_Here!$C$4,"EXPIRED",IF(J10-Start_Here!$C$4<=Start_Here!$C$5,"Expires within reminder window","OK"))) -> OK | L10: =SUMIFS(Roster!$F$4:$F$60,Roster!$J$4:$J$60,A10,Roster!$M$4:$M$60,"<>Cancelled") -> 6
A11: W02 | B11: Ethan Clarke | C11: Support worker | D11: Direct support | E11: Melbourne | F11: Casual | G11: Wed-Sun | J11: 46721 | K11: =IF(J11="","",IF(J11<Start_Here!$C$4,"EXPIRED",IF(J11-Start_Here!$C$4<=Start_Here!$C$5,"Expires within reminder window","OK"))) -> OK | L11: =SUMIFS(Roster!$F$4:$F$60,Roster!$J$4:$J$60,A11,Roster!$M$4:$M$60,"<>Cancelled") -> 2
A12: W03 | B12: Sophie Lam | C12: Support worker | D12: Direct support | E12: Melbourne | F12: Full-time | G12: Mon-Fri | J12: 46629 | K12: =IF(J12="","",IF(J12<Start_Here!$C$4,"EXPIRED",IF(J12-Start_Here!$C$4<=Start_Here!$C$5,"Expires within reminder window","OK"))) -> OK | L12: =SUMIFS(Roster!$F$4:$F$60,Roster!$J$4:$J$60,A12,Roster!$M$4:$M$60,"<>Cancelled") -> 8
A13: W04 | B13: Rico Santos | C13: Support worker | D13: Direct support | E13: Melbourne | F13: Casual | G13: Mon-Sat | J13: 46346 | K13: =IF(J13="","",IF(J13<Start_Here!$C$4,"EXPIRED",IF(J13-Start_Here!$C$4<=Start_Here!$C$5,"Expires within reminder window","OK"))) -> Expires within reminder window | L13: =SUMIFS(Roster!$F$4:$F$60,Roster!$J$4:$J$60,A13,Roster!$M$4:$M$60,"<>Cancelled") -> 0
A14: W05 | B14: Amelia Fraser | C14: Support worker | D14: Direct support | E14: Melbourne | F14: Full-time | G14: Mon-Fri | H14: 46330 | I14: 46331 | J14: 46762 | K14: =IF(J14="","",IF(J14<Start_Here!$C$4,"EXPIRED",IF(J14-Start_Here!$C$4<=Start_Here!$C$5,"Expires within reminder window","OK"))) -> OK | L14: =SUMIFS(Roster!$F$4:$F$60,Roster!$J$4:$J$60,A14,Roster!$M$4:$M$60,"<>Cancelled") -> 4 | M14: Approved leave
A15: W06 | B15: Kwame Mensah | C15: Support worker | D15: Direct support | E15: Melbourne | F15: Part-time | G15: Tue-Sat | J15: 46519 | K15: =IF(J15="","",IF(J15<Start_Here!$C$4,"EXPIRED",IF(J15-Start_Here!$C$4<=Start_Here!$C$5,"Expires within reminder window","OK"))) -> OK | L15: =SUMIFS(Roster!$F$4:$F$60,Roster!$J$4:$J$60,A15,Roster!$M$4:$M$60,"<>Cancelled") -> 7
A16: W07 | B16: Isla Barrett | C16: Support worker | D16: Direct support | E16: Gold Coast | F16: Part-time | G16: Mon-Sat | J16: 46639 | K16: =IF(J16="","",IF(J16<Start_Here!$C$4,"EXPIRED",IF(J16-Start_Here!$C$4<=Start_Here!$C$5,"Expires within reminder window","OK"))) -> OK | L16: =SUMIFS(Roster!$F$4:$F$60,Roster!$J$4:$J$60,A16,Roster!$M$4:$M$60,"<>Cancelled") -> 11
A17: W08 | B17: Noah Kelly | C17: Support worker | D17: Direct support | E17: Gold Coast | F17: Casual | G17: Wed-Sun | J17: 46320 | K17: =IF(J17="","",IF(J17<Start_Here!$C$4,"EXPIRED",IF(J17-Start_Here!$C$4<=Start_Here!$C$5,"Expires within reminder window","OK"))) -> EXPIRED | L17: =SUMIFS(Roster!$F$4:$F$60,Roster!$J$4:$J$60,A17,Roster!$M$4:$M$60,"<>Cancelled") -> 4
A18: W09 | B18: Mei Tanaka | C18: Support worker | D18: Direct support | E18: Melbourne | F18: Casual | G18: Sat-Sun | J18: 46436 | K18: =IF(J18="","",IF(J18<Start_Here!$C$4,"EXPIRED",IF(J18-Start_Here!$C$4<=Start_Here!$C$5,"Expires within reminder window","OK"))) -> OK | L18: =SUMIFS(Roster!$F$4:$F$60,Roster!$J$4:$J$60,A18,Roster!$M$4:$M$60,"<>Cancelled") -> 8
A19: W10 | B19: Liam Doyle | C19: Support worker | D19: Direct support | E19: Melbourne | F19: Part-time | G19: Mon-Fri | J19: 46539 | K19: =IF(J19="","",IF(J19<Start_Here!$C$4,"EXPIRED",IF(J19-Start_Here!$C$4<=Start_Here!$C$5,"Expires within reminder window","OK"))) -> OK | L19: =SUMIFS(Roster!$F$4:$F$60,Roster!$J$4:$J$60,A19,Roster!$M$4:$M$60,"<>Cancelled") -> 4
A20: W11 | B20: Farah Hussein | C20: Support worker | D20: Direct support | E20: Melbourne | F20: Casual | G20: Sat-Sun | J20: 46847 | K20: =IF(J20="","",IF(J20<Start_Here!$C$4,"EXPIRED",IF(J20-Start_Here!$C$4<=Start_Here!$C$5,"Expires within reminder window","OK"))) -> OK | L20: =SUMIFS(Roster!$F$4:$F$60,Roster!$J$4:$J$60,A20,Roster!$M$4:$M$60,"<>Cancelled") -> 4
A21: W12 | B21: George Papadakis | C21: Support worker | D21: Direct support | E21: Melbourne | F21: Part-time | G21: Tue, Sun | J21: 46733 | K21: =IF(J21="","",IF(J21<Start_Here!$C$4,"EXPIRED",IF(J21-Start_Here!$C$4<=Start_Here!$C$5,"Expires within reminder window","OK"))) -> OK | L21: =SUMIFS(Roster!$F$4:$F$60,Roster!$J$4:$J$60,A21,Roster!$M$4:$M$60,"<>Cancelled") -> 8
A22: A01 | B22: Naomi Cheung | C22: Occupational therapist (contractor) | D22: Allied health | E22: Melbourne | F22: Contractor | G22: Tue, Thu | K22: =IF(J22="","",IF(J22<Start_Here!$C$4,"EXPIRED",IF(J22-Start_Here!$C$4<=Start_Here!$C$5,"Expires within reminder window","OK"))) | L22: =SUMIFS(Roster!$F$4:$F$60,Roster!$J$4:$J$60,A22,Roster!$M$4:$M$60,"<>Cancelled") -> 1 | M22: Confirm any screening requirement with the manager
A23: A02 | B23: Peter Lindqvist | C23: Physiotherapist (contractor) | D23: Allied health | E23: Melbourne | F23: Contractor | G23: Mon, Wed | K23: =IF(J23="","",IF(J23<Start_Here!$C$4,"EXPIRED",IF(J23-Start_Here!$C$4<=Start_Here!$C$5,"Expires within reminder window","OK"))) | L23: =SUMIFS(Roster!$F$4:$F$60,Roster!$J$4:$J$60,A23,Roster!$M$4:$M$60,"<>Cancelled") -> 3 | M23: Confirm any screening requirement with the manager
A24: A03 | B24: Dana Okafor | C24: Psychologist (contractor) | D24: Allied health | E24: Melbourne | F24: Contractor | G24: Tue, Fri | K24: =IF(J24="","",IF(J24<Start_Here!$C$4,"EXPIRED",IF(J24-Start_Here!$C$4<=Start_Here!$C$5,"Expires within reminder window","OK"))) | L24: =SUMIFS(Roster!$F$4:$F$60,Roster!$J$4:$J$60,A24,Roster!$M$4:$M$60,"<>Cancelled") -> 1 | M24: Confirm any screening requirement with the manager
A25: W13 | B25: Ava McKenzie | C25: Support worker | D25: Direct support | E25: Gold Coast | F25: Casual | G25: Mon-Fri | J25: 46568 | K25: =IF(J25="","",IF(J25<Start_Here!$C$4,"EXPIRED",IF(J25-Start_Here!$C$4<=Start_Here!$C$5,"Expires within reminder window","OK"))) -> OK | L25: =SUMIFS(Roster!$F$4:$F$60,Roster!$J$4:$J$60,A25,Roster!$M$4:$M$60,"<>Cancelled") -> 0 | M25: M15 capstone candidate; fictional assessment record.

Sheet Roster
A1: Practice week roster (Mon 2 to Sun 8 Nov 2026)
A2: Times are local to the site. Look for problems, then note them in the yellow column. Names and hours are looked up for you.
A3: Shift ID | B3: Date | C3: Day | D3: Start | E3: End | F3: Hours | G3: Participant ID | H3: Participant name | I3: Support type | J3: Worker ID | K3: Worker name | L3: Site | M3: Status | N3: Time zone entered | O3: Your notes
A4: R01 | B4: 46328 | C4: =TEXT(B4,"ddd") -> Mon | D4: 0.375 | E4: 0.54166667 | F4: =IF(AND(ISNUMBER(D4),ISNUMBER(E4)),(E4-D4)*24,"") -> 4 | G4: P04 | H4: =IF(G4="","",IFERROR(INDEX(Participants!$B$4:$B$15,MATCH(G4,Participants!$A$4:$A$15,0)),"NOT FOUND")) -> Tom Nguyen | I4: Daily living | J4: W03 | K4: =IF(J4="","",IFERROR(INDEX(Staff!$B$4:$B$40,MATCH(J4,Staff!$A$4:$A$40,0)),"NOT FOUND")) -> Sophie Lam | L4: Melbourne | M4: Confirmed | N4: AEDT
A5: R02 | B5: 46328 | C5: =TEXT(B5,"ddd") -> Mon | D5: 0.5 | E5: 0.66666667 | F5: =IF(AND(ISNUMBER(D5),ISNUMBER(E5)),(E5-D5)*24,"") -> 4 | G5: P06 | H5: =IF(G5="","",IFERROR(INDEX(Participants!$B$4:$B$15,MATCH(G5,Participants!$A$4:$A$15,0)),"NOT FOUND")) -> Jack O'Connor | I5: Daily living | J5: W03 | K5: =IF(J5="","",IFERROR(INDEX(Staff!$B$4:$B$40,MATCH(J5,Staff!$A$4:$A$40,0)),"NOT FOUND")) -> Sophie Lam | L5: Melbourne | M5: Confirmed | N5: AEDT
A6: R03 | B6: 46328 | C6: =TEXT(B6,"ddd") -> Mon | D6: 0.41666667 | E6: 0.5 | F6: =IF(AND(ISNUMBER(D6),ISNUMBER(E6)),(E6-D6)*24,"") -> 2 | G6: P01 | H6: =IF(G6="","",IFERROR(INDEX(Participants!$B$4:$B$15,MATCH(G6,Participants!$A$4:$A$15,0)),"NOT FOUND")) -> Marisol Reyes | I6: Community access | J6: W01 | K6: =IF(J6="","",IFERROR(INDEX(Staff!$B$4:$B$40,MATCH(J6,Staff!$A$4:$A$40,0)),"NOT FOUND")) -> Joy Villanueva | L6: Melbourne | M6: Confirmed | N6: AEDT
A7: R04 | B7: 46328 | C7: =TEXT(B7,"ddd") -> Mon | D7: 0.58333333 | E7: 0.66666667 | F7: =IF(AND(ISNUMBER(D7),ISNUMBER(E7)),(E7-D7)*24,"") -> 2 | G7: P02 | H7: =IF(G7="","",IFERROR(INDEX(Participants!$B$4:$B$15,MATCH(G7,Participants!$A$4:$A$15,0)),"NOT FOUND")) -> Daniel Whitfield | I7: Daily living | J7: W10 | K7: =IF(J7="","",IFERROR(INDEX(Staff!$B$4:$B$40,MATCH(J7,Staff!$A$4:$A$40,0)),"NOT FOUND")) -> Liam Doyle | L7: Melbourne | M7: Confirmed | N7: AEDT
A8: R05 | B8: 46329 | C8: =TEXT(B8,"ddd") -> Tue | D8: 0.375 | E8: 0.54166667 | F8: =IF(AND(ISNUMBER(D8),ISNUMBER(E8)),(E8-D8)*24,"") -> 4 | G8: P06 | H8: =IF(G8="","",IFERROR(INDEX(Participants!$B$4:$B$15,MATCH(G8,Participants!$A$4:$A$15,0)),"NOT FOUND")) -> Jack O'Connor | I8: Daily living | J8: W06 | K8: =IF(J8="","",IFERROR(INDEX(Staff!$B$4:$B$40,MATCH(J8,Staff!$A$4:$A$40,0)),"NOT FOUND")) -> Kwame Mensah | L8: Melbourne | M8: Confirmed | N8: AEDT
A9: R06 | B9: 46329 | C9: =TEXT(B9,"ddd") -> Tue | D9: 0.41666667 | E9: 0.58333333 | F9: =IF(AND(ISNUMBER(D9),ISNUMBER(E9)),(E9-D9)*24,"") -> 4 | G9: P11 | H9: =IF(G9="","",IFERROR(INDEX(Participants!$B$4:$B$15,MATCH(G9,Participants!$A$4:$A$15,0)),"NOT FOUND")) -> Hannah Kowalski | I9: Daily living | J9: W12 | K9: =IF(J9="","",IFERROR(INDEX(Staff!$B$4:$B$40,MATCH(J9,Staff!$A$4:$A$40,0)),"NOT FOUND")) -> George Papadakis | L9: Melbourne | M9: Confirmed | N9: AEDT
A10: R07 | B10: 46329 | C10: =TEXT(B10,"ddd") -> Tue | D10: 0.375 | E10: 0.5 | F10: =IF(AND(ISNUMBER(D10),ISNUMBER(E10)),(E10-D10)*24,"") -> 3 | G10: P08 | H10: =IF(G10="","",IFERROR(INDEX(Participants!$B$4:$B$15,MATCH(G10,Participants!$A$4:$A$15,0)),"NOT FOUND")) -> Ben Taylor | I10: Community access | J10: W07 | K10: =IF(J10="","",IFERROR(INDEX(Staff!$B$4:$B$40,MATCH(J10,Staff!$A$4:$A$40,0)),"NOT FOUND")) -> Isla Barrett | L10: Gold Coast | M10: Confirmed | N10: AEST
A11: R08 | B11: 46330 | C11: =TEXT(B11,"ddd") -> Wed | D11: 0.41666667 | E11: 0.58333333 | F11: =IF(AND(ISNUMBER(D11),ISNUMBER(E11)),(E11-D11)*24,"") -> 4 | G11: P02 | H11: =IF(G11="","",IFERROR(INDEX(Participants!$B$4:$B$15,MATCH(G11,Participants!$A$4:$A$15,0)),"NOT FOUND")) -> Daniel Whitfield | I11: Daily living | J11: W05 | K11: =IF(J11="","",IFERROR(INDEX(Staff!$B$4:$B$40,MATCH(J11,Staff!$A$4:$A$40,0)),"NOT FOUND")) -> Amelia Fraser | L11: Melbourne | M11: Confirmed | N11: AEDT
A12: R09 | B12: 46330 | C12: =TEXT(B12,"ddd") -> Wed | D12: 0.375 | E12: 0.54166667 | F12: =IF(AND(ISNUMBER(D12),ISNUMBER(E12)),(E12-D12)*24,"") -> 4 | G12: P08 | H12: =IF(G12="","",IFERROR(INDEX(Participants!$B$4:$B$15,MATCH(G12,Participants!$A$4:$A$15,0)),"NOT FOUND")) -> Ben Taylor | I12: Community access | J12: W08 | K12: =IF(J12="","",IFERROR(INDEX(Staff!$B$4:$B$40,MATCH(J12,Staff!$A$4:$A$40,0)),"NOT FOUND")) -> Noah Kelly | L12: Gold Coast | M12: Confirmed | N12: AEST
A13: R10 | B13: 46330 | C13: =TEXT(B13,"ddd") -> Wed | D13: 0.54166667 | E13: 0.625 | F13: =IF(AND(ISNUMBER(D13),ISNUMBER(E13)),(E13-D13)*24,"") -> 2 | G13: P12 | H13: =IF(G13="","",IFERROR(INDEX(Participants!$B$4:$B$15,MATCH(G13,Participants!$A$4:$A$15,0)),"NOT FOUND")) -> Ravi Patel | I13: Physiotherapy | J13: A02 | K13: =IF(J13="","",IFERROR(INDEX(Staff!$B$4:$B$40,MATCH(J13,Staff!$A$4:$A$40,0)),"NOT FOUND")) -> Peter Lindqvist | L13: Melbourne | M13: Confirmed | N13: AEDT
A14: R11 | B14: 46330 | C14: =TEXT(B14,"ddd") -> Wed | D14: 0.375 | E14: 0.41666667 | F14: =IF(AND(ISNUMBER(D14),ISNUMBER(E14)),(E14-D14)*24,"") -> 1 | G14: P01 | H14: =IF(G14="","",IFERROR(INDEX(Participants!$B$4:$B$15,MATCH(G14,Participants!$A$4:$A$15,0)),"NOT FOUND")) -> Marisol Reyes | I14: Physiotherapy | J14: A02 | K14: =IF(J14="","",IFERROR(INDEX(Staff!$B$4:$B$40,MATCH(J14,Staff!$A$4:$A$40,0)),"NOT FOUND")) -> Peter Lindqvist | L14: Melbourne | M14: Confirmed | N14: AEDT
A15: R12 | B15: 46331 | C15: =TEXT(B15,"ddd") -> Thu | D15: 0.54166667 | E15: 0.70833333 | F15: =IF(AND(ISNUMBER(D15),ISNUMBER(E15)),(E15-D15)*24,"") -> 4 | G15: P06 | H15: =IF(G15="","",IFERROR(INDEX(Participants!$B$4:$B$15,MATCH(G15,Participants!$A$4:$A$15,0)),"NOT FOUND")) -> Jack O'Connor | I15: Daily living | K15: =IF(J15="","",IFERROR(INDEX(Staff!$B$4:$B$40,MATCH(J15,Staff!$A$4:$A$40,0)),"NOT FOUND")) | L15: Melbourne | M15: Unfilled | N15: AEDT
A16: R13 | B16: 46331 | C16: =TEXT(B16,"ddd") -> Thu | D16: 0.41666667 | E16: 0.45833333 | F16: =IF(AND(ISNUMBER(D16),ISNUMBER(E16)),(E16-D16)*24,"") -> 1 | G16: P04 | H16: =IF(G16="","",IFERROR(INDEX(Participants!$B$4:$B$15,MATCH(G16,Participants!$A$4:$A$15,0)),"NOT FOUND")) -> Tom Nguyen | I16: Occupational therapy | J16: A01 | K16: =IF(J16="","",IFERROR(INDEX(Staff!$B$4:$B$40,MATCH(J16,Staff!$A$4:$A$40,0)),"NOT FOUND")) -> Naomi Cheung | L16: Melbourne | M16: Confirmed | N16: AEDT
A17: R14 | B17: 46331 | C17: =TEXT(B17,"ddd") -> Thu | D17: 0.375 | E17: 0.54166667 | F17: =IF(AND(ISNUMBER(D17),ISNUMBER(E17)),(E17-D17)*24,"") -> 4 | G17: P11 | H17: =IF(G17="","",IFERROR(INDEX(Participants!$B$4:$B$15,MATCH(G17,Participants!$A$4:$A$15,0)),"NOT FOUND")) -> Hannah Kowalski | I17: Daily living | J17: W01 | K17: =IF(J17="","",IFERROR(INDEX(Staff!$B$4:$B$40,MATCH(J17,Staff!$A$4:$A$40,0)),"NOT FOUND")) -> Joy Villanueva | L17: Melbourne | M17: Confirmed | N17: AEDT
A18: R15 | B18: 46331 | C18: =TEXT(B18,"ddd") -> Thu | D18: 0.375 | E18: 0.5 | F18: =IF(AND(ISNUMBER(D18),ISNUMBER(E18)),(E18-D18)*24,"") -> 3 | G18: P05 | H18: =IF(G18="","",IFERROR(INDEX(Participants!$B$4:$B$15,MATCH(G18,Participants!$A$4:$A$15,0)),"NOT FOUND")) -> Priya Nair | I18: Community participation | J18: W06 | K18: =IF(J18="","",IFERROR(INDEX(Staff!$B$4:$B$40,MATCH(J18,Staff!$A$4:$A$40,0)),"NOT FOUND")) -> Kwame Mensah | L18: Melbourne | M18: Confirmed | N18: AEDT
A19: R16 | B19: 46332 | C19: =TEXT(B19,"ddd") -> Fri | D19: 0.41666667 | E19: 0.5 | F19: =IF(AND(ISNUMBER(D19),ISNUMBER(E19)),(E19-D19)*24,"") -> 2 | G19: P04 | H19: =IF(G19="","",IFERROR(INDEX(Participants!$B$4:$B$15,MATCH(G19,Participants!$A$4:$A$15,0)),"NOT FOUND")) -> Tom Nguyen | I19: Daily living | J19: W03 | K19: =IF(J19="","",IFERROR(INDEX(Staff!$B$4:$B$40,MATCH(J19,Staff!$A$4:$A$40,0)),"NOT FOUND")) -> Sophie Lam | L19: Melbourne | M19: Cancelled | N19: AEDT | O19: Participant cancelled at 8:30 am the same day
A20: R17 | B20: 46332 | C20: =TEXT(B20,"ddd") -> Fri | D20: 0.375 | E20: 0.54166667 | F20: =IF(AND(ISNUMBER(D20),ISNUMBER(E20)),(E20-D20)*24,"") -> 4 | G20: P08 | H20: =IF(G20="","",IFERROR(INDEX(Participants!$B$4:$B$15,MATCH(G20,Participants!$A$4:$A$15,0)),"NOT FOUND")) -> Ben Taylor | I20: Community access | J20: W07 | K20: =IF(J20="","",IFERROR(INDEX(Staff!$B$4:$B$40,MATCH(J20,Staff!$A$4:$A$40,0)),"NOT FOUND")) -> Isla Barrett | L20: Gold Coast | M20: Confirmed | N20: AEST
A21: R18 | B21: 46332 | C21: =TEXT(B21,"ddd") -> Fri | D21: 0.41666667 | E21: 0.5 | F21: =IF(AND(ISNUMBER(D21),ISNUMBER(E21)),(E21-D21)*24,"") -> 2 | G21: P12 | H21: =IF(G21="","",IFERROR(INDEX(Participants!$B$4:$B$15,MATCH(G21,Participants!$A$4:$A$15,0)),"NOT FOUND")) -> Ravi Patel | I21: Daily living | J21: W10 | K21: =IF(J21="","",IFERROR(INDEX(Staff!$B$4:$B$40,MATCH(J21,Staff!$A$4:$A$40,0)),"NOT FOUND")) -> Liam Doyle | L21: Melbourne | M21: Confirmed | N21: AEDT
A22: R19 | B22: 46332 | C22: =TEXT(B22,"ddd") -> Fri | D22: 0.375 | E22: 0.41666667 | F22: =IF(AND(ISNUMBER(D22),ISNUMBER(E22)),(E22-D22)*24,"") -> 1 | G22: P07 | H22: =IF(G22="","",IFERROR(INDEX(Participants!$B$4:$B$15,MATCH(G22,Participants!$A$4:$A$15,0)),"NOT FOUND")) -> Lucia Fernandez | I22: Psychology | J22: A03 | K22: =IF(J22="","",IFERROR(INDEX(Staff!$B$4:$B$40,MATCH(J22,Staff!$A$4:$A$40,0)),"NOT FOUND")) -> Dana Okafor | L22: Melbourne | M22: Confirmed | N22: AEDT
A23: R20 | B23: 46333 | C23: =TEXT(B23,"ddd") -> Sat | D23: 0.375 | E23: 0.54166667 | F23: =IF(AND(ISNUMBER(D23),ISNUMBER(E23)),(E23-D23)*24,"") -> 4 | G23: P08 | H23: =IF(G23="","",IFERROR(INDEX(Participants!$B$4:$B$15,MATCH(G23,Participants!$A$4:$A$15,0)),"NOT FOUND")) -> Ben Taylor | I23: Community access | J23: W07 | K23: =IF(J23="","",IFERROR(INDEX(Staff!$B$4:$B$40,MATCH(J23,Staff!$A$4:$A$40,0)),"NOT FOUND")) -> Isla Barrett | L23: Gold Coast | M23: Confirmed | N23: AEDT
A24: R21 | B24: 46333 | C24: =TEXT(B24,"ddd") -> Sat | D24: 0.375 | E24: 0.54166667 | F24: =IF(AND(ISNUMBER(D24),ISNUMBER(E24)),(E24-D24)*24,"") -> 4 | G24: P01 | H24: =IF(G24="","",IFERROR(INDEX(Participants!$B$4:$B$15,MATCH(G24,Participants!$A$4:$A$15,0)),"NOT FOUND")) -> Marisol Reyes | I24: Community access | J24: W09 | K24: =IF(J24="","",IFERROR(INDEX(Staff!$B$4:$B$40,MATCH(J24,Staff!$A$4:$A$40,0)),"NOT FOUND")) -> Mei Tanaka | L24: Melbourne | M24: Confirmed | N24: AEDT
A25: R22 | B25: 46333 | C25: =TEXT(B25,"ddd") -> Sat | D25: 0.41666667 | E25: 0.58333333 | F25: =IF(AND(ISNUMBER(D25),ISNUMBER(E25)),(E25-D25)*24,"") -> 4 | G25: P11 | H25: =IF(G25="","",IFERROR(INDEX(Participants!$B$4:$B$15,MATCH(G25,Participants!$A$4:$A$15,0)),"NOT FOUND")) -> Hannah Kowalski | I25: Daily living | J25: W11 | K25: =IF(J25="","",IFERROR(INDEX(Staff!$B$4:$B$40,MATCH(J25,Staff!$A$4:$A$40,0)),"NOT FOUND")) -> Farah Hussein | L25: Melbourne | M25: Confirmed | N25: AEDT
A26: R23 | B26: 46334 | C26: =TEXT(B26,"ddd") -> Sun | D26: 0.41666667 | E26: 0.58333333 | F26: =IF(AND(ISNUMBER(D26),ISNUMBER(E26)),(E26-D26)*24,"") -> 4 | G26: P12 | H26: =IF(G26="","",IFERROR(INDEX(Participants!$B$4:$B$15,MATCH(G26,Participants!$A$4:$A$15,0)),"NOT FOUND")) -> Ravi Patel | I26: Daily living | J26: W09 | K26: =IF(J26="","",IFERROR(INDEX(Staff!$B$4:$B$40,MATCH(J26,Staff!$A$4:$A$40,0)),"NOT FOUND")) -> Mei Tanaka | L26: Melbourne | M26: Confirmed | N26: AEDT
A27: R24 | B27: 46334 | C27: =TEXT(B27,"ddd") -> Sun | D27: 0.375 | E27: 0.54166667 | F27: =IF(AND(ISNUMBER(D27),ISNUMBER(E27)),(E27-D27)*24,"") -> 4 | G27: P06 | H27: =IF(G27="","",IFERROR(INDEX(Participants!$B$4:$B$15,MATCH(G27,Participants!$A$4:$A$15,0)),"NOT FOUND")) -> Jack O'Connor | I27: Daily living | J27: W12 | K27: =IF(J27="","",IFERROR(INDEX(Staff!$B$4:$B$40,MATCH(J27,Staff!$A$4:$A$40,0)),"NOT FOUND")) -> George Papadakis | L27: Melbourne | M27: Confirmed | N27: AEDT
A28: R25 | B28: 46334 | C28: =TEXT(B28,"ddd") -> Sun | D28: 0.45833333 | E28: 0.54166667 | F28: =IF(AND(ISNUMBER(D28),ISNUMBER(E28)),(E28-D28)*24,"") -> 2 | G28: P02 | H28: =IF(G28="","",IFERROR(INDEX(Participants!$B$4:$B$15,MATCH(G28,Participants!$A$4:$A$15,0)),"NOT FOUND")) -> Daniel Whitfield | I28: Community access | J28: W02 | K28: =IF(J28="","",IFERROR(INDEX(Staff!$B$4:$B$40,MATCH(J28,Staff!$A$4:$A$40,0)),"NOT FOUND")) -> Ethan Clarke | L28: Melbourne | M28: Confirmed | N28: AEDT

Sheet Price_Table
A1: Price table (FICTIONAL, invented prices)
A2: These prices and codes are invented for practice. They are NOT real NDIS prices or item numbers. Real pricing changes, so learn where to check it (Module 8).
A3: Item code | B3: Description | C3: Support budget | D3: Category (fictional label) | E3: Unit | F3: Price limit (AUD, fictional) | G3: Effective from
A4: FX-DL-WD | B4: Daily living support - weekday daytime | C4: Core | D4: Daily life | E4: hour | F4: 60 | G4: 46204
A5: FX-DL-WE | B5: Daily living support - weekday evening | C5: Core | D5: Daily life | E5: hour | F5: 66 | G5: 46204
A6: FX-DL-SA | B6: Daily living support - Saturday | C6: Core | D6: Daily life | E6: hour | F6: 84 | G6: 46204
A7: FX-DL-SU | B7: Daily living support - Sunday | C7: Core | D7: Daily life | E7: hour | F7: 108 | G7: 46204
A8: FX-DL-PH | B8: Daily living support - public holiday | C8: Core | D8: Daily life | E8: hour | F8: 132 | G8: 46204
A9: FX-CA-WD | B9: Community access - weekday daytime | C9: Core | D9: Community | E9: hour | F9: 62 | G9: 46204
A10: FX-CA-SA | B10: Community access - Saturday | C10: Core | D10: Community | E10: hour | F10: 87 | G10: 46204
A11: FX-SC-01 | B11: Support coordination - standard | C11: Capacity Building | D11: Coordination | E11: hour | F11: 100 | G11: 46204
A12: FX-PM-SU | B12: Plan management - set-up | C12: Capacity Building | D12: Plan management | E12: each | F12: 200 | G12: 46204
A13: FX-PM-MO | B13: Plan management - monthly | C13: Capacity Building | D13: Plan management | E13: month | F13: 60 | G13: 46204
A14: FX-OT-01 | B14: Occupational therapy - standard session | C14: Capacity Building | D14: Therapy | E14: hour | F14: 190 | G14: 46204
A15: FX-PT-01 | B15: Physiotherapy - standard session | C15: Capacity Building | D15: Therapy | E15: hour | F15: 175 | G15: 46204
... A17: FX-TR-KM | B17: Provider travel - per kilometre | C17: Core | D17: Travel | E17: km | F17: 1 | G17: 46204
A24: Yellow rows: add new price versions here (see the pricing update email). Keep old prices for older dates.

Sheet Invoice_Batch
A1: Invoice batch to check (fictional)
A2: Learner task: check identity/onboarding, date/day type, item, qty, fictional rate/reference, management type, duplicates, service-delivery evidence and route-to. Then classify and explain. | B2: Decide: OK, Flag, Ask, or Escalate. Do not independently approve/reject/submit/dispute.
A3: Invoice # | B3: Service date | C3: Participant ID | D3: Participant name | E3: Plan management | F3: Item code | G3: Item description | H3: Qty | I3: Unit | J3: Rate charged | K3: Price limit (fictional) | L3: Line total | M3: Your check | N3: Your note
A4: INV-1001 | B4: 46321 | C4: P01 | D4: =IFERROR(INDEX(Participants!$B$4:$B$15,MATCH(C4,Participants!$A$4:$A$15,0)),"NOT FOUND") -> Marisol Reyes | E4: =IFERROR(INDEX(Participants!$D$4:$D$15,MATCH(C4,Participants!$A$4:$A$15,0)),"NOT FOUND") -> Plan-managed | F4: FX-CA-WD | G4: =IFERROR(INDEX(Price_Table!$B$4:$B$40,MATCH(F4,Price_Table!$A$4:$A$40,0)),"NOT FOUND") -> Community access - weekday daytime | H4: 2 | I4: =IFERROR(INDEX(Price_Table!$E$4:$E$40,MATCH(F4,Price_Table!$A$4:$A$40,0)),"") -> hour | J4: 62 | K4: =IFERROR(INDEX(Price_Table!$F$4:$F$40,MATCH(F4,Price_Table!$A$4:$A$40,0)),"") -> 62 | L4: =IF(AND(ISNUMBER(H4),ISNUMBER(J4)),H4*J4,"") -> 124
A5: INV-1002 | B5: 46321 | C5: P04 | D5: =IFERROR(INDEX(Participants!$B$4:$B$15,MATCH(C5,Participants!$A$4:$A$15,0)),"NOT FOUND") -> Tom Nguyen | E5: =IFERROR(INDEX(Participants!$D$4:$D$15,MATCH(C5,Participants!$A$4:$A$15,0)),"NOT FOUND") -> Plan-managed | F5: FX-DL-WD | G5: =IFERROR(INDEX(Price_Table!$B$4:$B$40,MATCH(F5,Price_Table!$A$4:$A$40,0)),"NOT FOUND") -> Daily living support - weekday daytime | H5: 4 | I5: =IFERROR(INDEX(Price_Table!$E$4:$E$40,MATCH(F5,Price_Table!$A$4:$A$40,0)),"") -> hour | J5: 60 | K5: =IFERROR(INDEX(Price_Table!$F$4:$F$40,MATCH(F5,Price_Table!$A$4:$A$40,0)),"") -> 60 | L5: =IF(AND(ISNUMBER(H5),ISNUMBER(J5)),H5*J5,"") -> 240
A6: INV-1003 | B6: 46322 | C6: P06 | D6: =IFERROR(INDEX(Participants!$B$4:$B$15,MATCH(C6,Participants!$A$4:$A$15,0)),"NOT FOUND") -> Jack O'Connor | E6: =IFERROR(INDEX(Participants!$D$4:$D$15,MATCH(C6,Participants!$A$4:$A$15,0)),"NOT FOUND") -> NDIA-managed | F6: FX-DL-WD | G6: =IFERROR(INDEX(Price_Table!$B$4:$B$40,MATCH(F6,Price_Table!$A$4:$A$40,0)),"NOT FOUND") -> Daily living support - weekday daytime | H6: 4 | I6: =IFERROR(INDEX(Price_Table!$E$4:$E$40,MATCH(F6,Price_Table!$A$4:$A$40,0)),"") -> hour | J6: 60 | K6: =IFERROR(INDEX(Price_Table!$F$4:$F$40,MATCH(F6,Price_Table!$A$4:$A$40,0)),"") -> 60 | L6: =IF(AND(ISNUMBER(H6),ISNUMBER(J6)),H6*J6,"") -> 240
A7: INV-1004 | B7: 46321 | C7: P01 | D7: =IFERROR(INDEX(Participants!$B$4:$B$15,MATCH(C7,Participants!$A$4:$A$15,0)),"NOT FOUND") -> Marisol Reyes | E7: =IFERROR(INDEX(Participants!$D$4:$D$15,MATCH(C7,Participants!$A$4:$A$15,0)),"NOT FOUND") -> Plan-managed | F7: FX-CA-WD | G7: =IFERROR(INDEX(Price_Table!$B$4:$B$40,MATCH(F7,Price_Table!$A$4:$A$40,0)),"NOT FOUND") -> Community access - weekday daytime | H7: 2 | I7: =IFERROR(INDEX(Price_Table!$E$4:$E$40,MATCH(F7,Price_Table!$A$4:$A$40,0)),"") -> hour | J7: 62 | K7: =IFERROR(INDEX(Price_Table!$F$4:$F$40,MATCH(F7,Price_Table!$A$4:$A$40,0)),"") -> 62 | L7: =IF(AND(ISNUMBER(H7),ISNUMBER(J7)),H7*J7,"") -> 124
A8: INV-1005 | B8: 46323 | C8: P02 | D8: =IFERROR(INDEX(Participants!$B$4:$B$15,MATCH(C8,Participants!$A$4:$A$15,0)),"NOT FOUND") -> Daniel Whitfield | E8: =IFERROR(INDEX(Participants!$D$4:$D$15,MATCH(C8,Participants!$A$4:$A$15,0)),"NOT FOUND") -> Self-managed | F8: FX-DL-WD | G8: =IFERROR(INDEX(Price_Table!$B$4:$B$40,MATCH(F8,Price_Table!$A$4:$A$40,0)),"NOT FOUND") -> Daily living support - weekday daytime | H8: 4 | I8: =IFERROR(INDEX(Price_Table!$E$4:$E$40,MATCH(F8,Price_Table!$A$4:$A$40,0)),"") -> hour | J8: 68 | K8: =IFERROR(INDEX(Price_Table!$F$4:$F$40,MATCH(F8,Price_Table!$A$4:$A$40,0)),"") -> 60 | L8: =IF(AND(ISNUMBER(H8),ISNUMBER(J8)),H8*J8,"") -> 272
A9: INV-1006 | B9: 46323 | C9: P12 | D9: =IFERROR(INDEX(Participants!$B$4:$B$15,MATCH(C9,Participants!$A$4:$A$15,0)),"NOT FOUND") -> Ravi Patel | E9: =IFERROR(INDEX(Participants!$D$4:$D$15,MATCH(C9,Participants!$A$4:$A$15,0)),"NOT FOUND") -> Plan-managed | F9: FX-PT-01 | G9: =IFERROR(INDEX(Price_Table!$B$4:$B$40,MATCH(F9,Price_Table!$A$4:$A$40,0)),"NOT FOUND") -> Physiotherapy - standard session | H9: 1 | I9: =IFERROR(INDEX(Price_Table!$E$4:$E$40,MATCH(F9,Price_Table!$A$4:$A$40,0)),"") -> hour | J9: 175 | K9: =IFERROR(INDEX(Price_Table!$F$4:$F$40,MATCH(F9,Price_Table!$A$4:$A$40,0)),"") -> 175 | L9: =IF(AND(ISNUMBER(H9),ISNUMBER(J9)),H9*J9,"") -> 175
A10: INV-1007 | B10: 46323 | C10: P07 | D10: =IFERROR(INDEX(Participants!$B$4:$B$15,MATCH(C10,Participants!$A$4:$A$15,0)),"NOT FOUND") -> Lucia Fernandez | E10: =IFERROR(INDEX(Participants!$D$4:$D$15,MATCH(C10,Participants!$A$4:$A$15,0)),"NOT FOUND") -> Plan-managed | F10: FX-PS-01 | G10: =IFERROR(INDEX(Price_Table!$B$4:$B$40,MATCH(F10,Price_Table!$A$4:$A$40,0)),"NOT FOUND") -> Psychology - standard session | H10: 1 | I10: =IFERROR(INDEX(Price_Table!$E$4:$E$40,MATCH(F10,Price_Table!$A$4:$A$40,0)),"") -> hour | J10: 220 | K10: =IFERROR(INDEX(Price_Table!$F$4:$F$40,MATCH(F10,Price_Table!$A$4:$A$40,0)),"") -> 220 | L10: =IF(AND(ISNUMBER(H10),ISNUMBER(J10)),H10*J10,"") -> 220
A11: INV-1008 | B11: 46324 | C11: P04 | D11: =IFERROR(INDEX(Participants!$B$4:$B$15,MATCH(C11,Participants!$A$4:$A$15,0)),"NOT FOUND") -> Tom Nguyen | E11: =IFERROR(INDEX(Participants!$D$4:$D$15,MATCH(C11,Participants!$A$4:$A$15,0)),"NOT FOUND") -> Plan-managed | F11: FX-OT-01 | G11: =IFERROR(INDEX(Price_Table!$B$4:$B$40,MATCH(F11,Price_Table!$A$4:$A$40,0)),"NOT FOUND") -> Occupational therapy - standard session | H11: 1 | I11: =IFERROR(INDEX(Price_Table!$E$4:$E$40,MATCH(F11,Price_Table!$A$4:$A$40,0)),"") -> hour | J11: 205 | K11: =IFERROR(INDEX(Price_Table!$F$4:$F$40,MATCH(F11,Price_Table!$A$4:$A$40,0)),"") -> 190 | L11: =IF(AND(ISNUMBER(H11),ISNUMBER(J11)),H11*J11,"") -> 205
A12: INV-1009 | B12: 46324 | C12: P08 | D12: =IFERROR(INDEX(Participants!$B$4:$B$15,MATCH(C12,Participants!$A$4:$A$15,0)),"NOT FOUND") -> Ben Taylor | E12: =IFERROR(INDEX(Participants!$D$4:$D$15,MATCH(C12,Participants!$A$4:$A$15,0)),"NOT FOUND") -> Plan-managed | F12: FX-CA-WD | G12: =IFERROR(INDEX(Price_Table!$B$4:$B$40,MATCH(F12,Price_Table!$A$4:$A$40,0)),"NOT FOUND") -> Community access - weekday daytime | H12: 4 | I12: =IFERROR(INDEX(Price_Table!$E$4:$E$40,MATCH(F12,Price_Table!$A$4:$A$40,0)),"") -> hour | J12: 62 | K12: =IFERROR(INDEX(Price_Table!$F$4:$F$40,MATCH(F12,Price_Table!$A$4:$A$40,0)),"") -> 62 | L12: =IF(AND(ISNUMBER(H12),ISNUMBER(J12)),H12*J12,"") -> 248
A13: INV-1010 | B13: 46324 | C13: P03 | D13: =IFERROR(INDEX(Participants!$B$4:$B$15,MATCH(C13,Participants!$A$4:$A$15,0)),"NOT FOUND") -> Aisha Rahman | E13: =IFERROR(INDEX(Participants!$D$4:$D$15,MATCH(C13,Participants!$A$4:$A$15,0)),"NOT FOUND") -> NDIA-managed | F13: FX-SC-01 | G13: =IFERROR(INDEX(Price_Table!$B$4:$B$40,MATCH(F13,Price_Table!$A$4:$A$40,0)),"NOT FOUND") -> Support coordination - standard | H13: 2 | I13: =IFERROR(INDEX(Price_Table!$E$4:$E$40,MATCH(F13,Price_Table!$A$4:$A$40,0)),"") -> hour | J13: 100 | K13: =IFERROR(INDEX(Price_Table!$F$4:$F$40,MATCH(F13,Price_Table!$A$4:$A$40,0)),"") -> 100 | L13: =IF(AND(ISNUMBER(H13),ISNUMBER(J13)),H13*J13,"") -> 200
A14: INV-1011 | B14: 46325 | C14: P11 | D14: =IFERROR(INDEX(Participants!$B$4:$B$15,MATCH(C14,Participants!$A$4:$A$15,0)),"NOT FOUND") -> Hannah Kowalski | E14: =IFERROR(INDEX(Participants!$D$4:$D$15,MATCH(C14,Participants!$A$4:$A$15,0)),"NOT FOUND") -> Self-managed | F14: FX-DL-WD | G14: =IFERROR(INDEX(Price_Table!$B$4:$B$40,MATCH(F14,Price_Table!$A$4:$A$40,0)),"NOT FOUND") -> Daily living support - weekday daytime | H14: 40 | I14: =IFERROR(INDEX(Price_Table!$E$4:$E$40,MATCH(F14,Price_Table!$A$4:$A$40,0)),"") -> hour | J14: 60 | K14: =IFERROR(INDEX(Price_Table!$F$4:$F$40,MATCH(F14,Price_Table!$A$4:$A$40,0)),"") -> 60 | L14: =IF(AND(ISNUMBER(H14),ISNUMBER(J14)),H14*J14,"") -> 2400
A15: INV-1012 | B15: 46325 | C15: P06 | D15: =IFERROR(INDEX(Participants!$B$4:$B$15,MATCH(C15,Participants!$A$4:$A$15,0)),"NOT FOUND") -> Jack O'Connor | E15: =IFERROR(INDEX(Participants!$D$4:$D$15,MATCH(C15,Participants!$A$4:$A$15,0)),"NOT FOUND") -> NDIA-managed | F15: FX-DL-WE | G15: =IFERROR(INDEX(Price_Table!$B$4:$B$40,MATCH(F15,Price_Table!$A$4:$A$40,0)),"NOT FOUND") -> Daily living support - weekday evening | H15: 3 | I15: =IFERROR(INDEX(Price_Table!$E$4:$E$40,MATCH(F15,Price_Table!$A$4:$A$40,0)),"") -> hour | J15: 66 | K15: =IFERROR(INDEX(Price_Table!$F$4:$F$40,MATCH(F15,Price_Table!$A$4:$A$40,0)),"") -> 66 | L15: =IF(AND(ISNUMBER(H15),ISNUMBER(J15)),H15*J15,"") -> 198
... A23: INV-1020 | B23: 46324 | C23: P05 | D23: =IFERROR(INDEX(Participants!$B$4:$B$15,MATCH(C23,Participants!$A$4:$A$15,0)),"NOT FOUND") -> Priya Nair | E23: =IFERROR(INDEX(Participants!$D$4:$D$15,MATCH(C23,Participants!$A$4:$A$15,0)),"NOT FOUND") -> Self-managed | F23: FX-CA-WD | G23: =IFERROR(INDEX(Price_Table!$B$4:$B$40,MATCH(F23,Price_Table!$A$4:$A$40,0)),"NOT FOUND") -> Community access - weekday daytime | H23: 3 | I23: =IFERROR(INDEX(Price_Table!$E$4:$E$40,MATCH(F23,Price_Table!$A$4:$A$40,0)),"") -> hour | J23: 62 | K23: =IFERROR(INDEX(Price_Table!$F$4:$F$40,MATCH(F23,Price_Table!$A$4:$A$40,0)),"") -> 62 | L23: =IF(AND(ISNUMBER(H23),ISNUMBER(J23)),H23*J23,"") -> 186
A25: Batch total | L25: =SUM(L4:L23) -> 6386
A26: Number of lines | L26: =COUNTA(A4:A23) -> 20

Sheet Inbox
A1: Shared inbox (fictional): the practice week
A2: Times are Melbourne time. Work through the emails in order. Decide what you can do yourself and what you must pass on.
A3: ID | B3: Received (Melbourne time) | C3: From | D3: Subject | E3: Message | F3: Your priority | G3: What you will do | H3: Who you will escalate to (if anyone) | I3: Done?
A4: E01 | B4: Mon 2 Nov, 7:15 am | C4: Joy Villanueva (support worker) | D4: Can't work today | E4: Hi, I woke up unwell and can't do my 10 am shift with Marisol today. Sorry for the late notice. Can someone cover?
A5: E02 | B5: Mon 2 Nov, 8:40 am | C5: Sophie Lam (support worker) | D5: Two shifts at once? | E5: Hi, my roster shows Tom from 9 to 1 and Jack from 12 to 4 today. I can't be in two places. Which one should I do?
A6: E03 | B6: Mon 2 Nov, 9:05 am | C6: Anna Mitchell (parent of a referral) | D6: Referral for my daughter | E6: Hello, my daughter Grace was recently approved for the NDIS. Do you have space for community access support, and what does the NDIS cover? Thanks.
A7: E04 | B7: Mon 2 Nov, 9:30 am | C7: Rhonda Blake (operations manager) | D7: Screening checks this week | E7: Please list any workers whose screening check has expired or expires soon. I need the names, the dates, and which shifts they are rostered for this week.
A8: E05 | B8: Mon 2 Nov, 10:10 am | C8: Olivia Grant (plan manager) | D8: Invoice batch to check | E8: Before I approve the batch, please check it and list anything that looks wrong or that you're unsure about. It's on the Invoice_Batch tab.
A9: E06 | B9: Mon 2 Nov, 11:00 am | C9: Kim Anders (external plan manager for Tom) | D9: Invoice INV-1008 | E9: Hi, invoice INV-1008 for Tom's OT session looks higher than the limit for that item. Can you confirm the rate?
A10: E07 | B10: Mon 2 Nov, 12:20 pm | C10: Jamal Ortiz (admin officer) | D10: Oops, wrong email | E10: I think I sent Marisol's roster to Priya's email address by mistake about ten minutes ago. What should I do?
A11: E08 | B11: Mon 2 Nov, 1:45 pm | C11: Callum Reid (director) | D11: Post for our page | E11: Can you draft a short, friendly post about our new Saturday community group? Please don't include any participant names or photos.
A12: E09 | B12: Tue 3 Nov, 7:50 am | C12: Ben Taylor (participant) | D12: Is today's support on? | E12: Is my 9 am support today still on? My cousin in Melbourne says today is a public holiday.
A13: E10 | B13: Tue 3 Nov, 9:15 am | C13: Priya Nair (participant) | D13: Copies of my records | E13: Hi, I'd like a copy of all the information Wattlebird holds about me. Can you send it to me by Friday?
A14: E11 | B14: Tue 3 Nov, 10:30 am | C14: Daniel Whitfield (participant) | D14: Receipts | E14: I manage my own plan. Where do I send your invoices, and what should I keep so I can claim?
A15: E12 | B15: Tue 3 Nov, 2:00 pm | C15: Rhonda Blake (operations manager) | D15: Pricing update | E15: A pricing update has been announced (fictional). From Monday 9 Nov, the limit for FX-DL-WD becomes $62.00 and FX-CA-WD becomes $64.00. Please update our price table and keep the old prices for older dates.
... A27: E24 | B27: Sun 8 Nov, 6:30 pm | C27: Rhonda Blake (operations manager) | D27: Audit next month | E27: An audit is coming next month. Please tidy the incident and complaint logs and list any gaps by Wednesday.

Sheet Task_Board
A1: My task board
A2: One row per task. The grey row is an example.
A3: Task | B3: Related email ID | C3: Owner | D3: Due | E3: Status | F3: Notes
A4: Ask Rhonda who covers Monday's 10 am shift | B4: E01 | C4: Me | D4: 46328 | E4: To do | F4: Joy is unwell. Suggest two possible cover options.

Sheet Incident_Log
A1: Incident log (fictional)
A2: Record only what was reported, in plain facts. You do NOT decide whether an incident is reportable. The manager fills in that column. The grey row is an example.
A3: Log ID | B3: Date and time of incident | C3: Site | D3: Participant ID | E3: Worker ID | F3: What was reported (facts only) | G3: Type, as described by the reporter | H3: Immediate actions, as reported | I3: Escalated to | J3: Date and time escalated | K3: Manager's decision (manager fills in) | L3: Status | M3: Notes
A4: EX-001 | B4: Tue 20 Oct 2026, 11:30 am | C4: Melbourne | D4: P02 | E4: W10 | F4: Worker reported that a cup was dropped and broken in the kitchen. No one was hurt. | G4: Minor property damage | H4: Worker cleaned up the pieces safely. | I4: Rhonda Blake | J4: Tue 20 Oct 2026, 11:50 am | L4: Escalated | M4: Example only

Sheet Complaints_Log
A1: Complaints log (fictional)
A2: Record the complaint neutrally and pass it on. Don't judge whether it is justified. The grey row is an example.
A3: Log ID | B3: Date received | C3: How received | D3: Complainant | E3: Related participant ID | F3: Summary (neutral wording) | G3: Immediate action | H3: Escalated to | I3: Date escalated | J3: Status | K3: Outcome (manager fills in)
A4: EX-001 | B4: 46314 | C4: Email | D4: Participant (P05) | E4: P05 | F4: Participant says the roster change was not communicated before the shift. | G4: Acknowledged receipt and passed to the manager. | H4: Rhonda Blake | I4: 46314 | J4: Escalated

Sheet Follow_Up_Log
A1: Follow-Up & Handover Log
A2: Use for open practice work. Sending a message is not automatically closure.
A4: Task ID | B4: Related Item | C4: Outstanding Item | D4: Owner | E4: Next Action | F4: Channel | G4: Follow-Up Date/Trigger | H4: Response/Outcome | I4: Closure Condition | J4: Status | K4: Learner Notes
A5: FU-001 | B5: E16 / Roster | C5: Thursday 1:00–5:00 pm shift still needs a worker | D5: Rhonda Blake | E5: Review the two feasible cover options and confirm the preferred option | F5: Email | G5: Before the affected shift / earlier if the owner responds | I5: Owner decision is recorded and the roster is updated or formally handed off. | J5: Open

Sheet Security_Extensions
A1: Security & Access Extensions
A2: Fictional practice scenarios for M12/M14. Real participant information belongs in provider-authorized workflows.
A3: Scenario ID | B3: Module | C3: Scenario | D3: Learner Task | E3: Your Classification | F3: Your Safe Action / Boundary | G3: Follow-Up / Closure
A4: Scenario ID | B4: Module | C4: Scenario | D4: Learner Task
A5: SEC-01 | B5: M12 | C5: A staff member asks you to paste a participant's message into a free public AI tool. | D5: Write the safe response and state what you will do next.
A6: SEC-02 | B6: M12 | C6: A roster containing participant names is accidentally emailed to the wrong recipient. | D6: List immediate containment and handoff steps.
A7: SEC-03 | B7: M14 | C7: A fictional system asks you to use a supervisor's login because your account has not been created. | D7: State how you proceed.
A8: SEC-04 | B8: M12 | C8: A client asks you to download participant files to your personal Google Drive so you can work faster. | D8: Respond and identify the correct workflow.

Sheet M6_Fictional_Plan
A1: M6 — Wattlebird Fictional Participant Plan
A2: FICTIONAL TRAINING DOCUMENT — NOT AN NDIS PLAN. Values and labels are invented for practice.
A4: Field | B4: Value | C4: Practice Note
A5: Participant | B5: Liam Dawson (P13) | C5: Fictional participant created for M6 practice.
A6: Site | B6: Melbourne | C6: Use site/time-zone information only for practice.
A7: Plan management | B7: Plan-managed | C7: Learner must identify management type before applying fictional pricing logic.
A8: Plan period | B8: 01/10/2026–30/09/2027 | C8: Fictional dates.
A9: Support budget 1 | B9: Core Supports | C9: Fictional budget label.
A10: Core allocation | B10: AUD 18,000 | C10: Fictional amount.
A11: Support budget 2 | B11: Capacity Building Supports | C11: Fictional budget label.
A12: Capacity Building allocation | B12: AUD 9,500 | C12: Fictional amount.
A13: Capital Supports | B13: None in this practice plan | C13: Do not infer real eligibility.
A14: Recurring Supports | B14: None in this practice plan | C14: Do not infer real eligibility.
A15: Service agreement | B15: Draft — manager review required | C15: VA may prepare/track; manager approves.
A16: Current task | B16: Match three sample support requests to fictional plan categories. | C16: Use this fictional plan only; real NDIS questions require current official verification.
A18: Fictional category breakdown
A19: Core Supports | B19: Daily living; community participation
A20: Capacity Building | B20: Allied-health-related fictional administrative examples
A22: Sample support requests
A23: SR-01 | B23: Weekly community access support | C23: Learner decides which fictional category is the closest administrative match.
A24: SR-02 | B24: Physiotherapy appointment | C24: Learner checks whether the fictional plan context contains enough information; do not infer clinical funding.
A25: SR-03 | B25: New support request with unclear category | C25: Learner identifies the ambiguity and writes a clarification question.

Sheet M7_Tickets
A1: M7 — Who Handles This?
A2: Ten fictional provider tickets. Identify owner, classification, next action, escalation path and follow-up.
A3: Ticket ID | B3: Incoming Request | C3: Your Classification | D3: Your Next Action | E3: What Will You Ask? | F3: Who Needs the Handoff? | G3: Follow-Up Trigger | H3: Closure Condition
A4: T01 | B4: Worker is sick and cannot cover today's participant shift.
A5: T02 | B5: Two shifts appear to overlap for the same worker.
A6: T03 | B6: Family asks what NDIS will fund for a new referral.
A7: T04 | B7: Plan manager asks VA to check an invoice batch.
A8: T05 | B8: Participant requests copies of all records.
A9: T06 | B9: Participant complains about repeated late worker arrivals.
A10: T07 | B10: Worker reports a participant injury during support.
A11: T08 | B11: Service agreement is due for renewal.
A12: T09 | B12: Worker screening status is expired or unclear.
A13: T10 | B13: Participant asks whether there is enough funding for future therapy.

Sheet M10_Onboarding
A1: M10 — Wattlebird Participant Onboarding Checklist
A2: FICTIONAL TRAINING TEMPLATE. VA prepares/tracks; authorized roles approve, negotiate, or decide.
A4: Checklist ID | B4: Onboarding Step | C4: Evidence / Field | D4: Owner | E4: Status | F4: Follow-Up Trigger | G4: Closure Condition
A5: ONB-01 | B5: Referral received | C5: Referral date/source recorded | D5: VA | E5: Not started | F5: If intake information is incomplete | G5: Referral logged and owner assigned.
A6: ONB-02 | B6: Participant identity/contact details | C6: Name, preferred contact, site, emergency contact field if provider procedure requires | D6: VA | E6: Not started | F6: Missing/unclear field | G6: Required fields verified by authorized process.
A7: ONB-03 | B7: Consent/authority | C7: Provider's approved consent/authority record | D7: Authorized owner | E7: Not started | F7: Missing/expired/unclear authority | G7: Authorized owner confirms valid record.
A8: ONB-04 | B8: Management type / plan context | C8: Management type and current plan information where authorized | D8: VA / coordinator | E8: Not started | F8: Unclear or unavailable | G8: Authorized owner confirms context.
A9: ONB-05 | B9: Requested supports | C9: Support request summary | D9: VA | E9: Not started | F9: Clinical/funding question arises | G9: Support coordinator confirms scope.
A10: ONB-06 | B10: Service agreement | C10: Draft/service agreement status | D10: VA prepares; manager reviews | E10: Not started | F10: Agreement due or missing | G10: Authorized person approves/returns agreement.
A11: ONB-07 | B11: Roster/availability | C11: Preferred schedule and worker requirements | D11: VA | E11: Not started | F11: No suitable availability | G11: Manager/coordinator chooses from feasible options.
A12: ONB-08 | B12: Safety / incident flags | C12: Record reported facts; no independent risk assessment | D12: VA records; manager handles | E12: Not started | F12: Safety concern reported | G12: Responsible owner acknowledges and follows procedure.
A13: ONB-09 | B13: Welcome / communication | C13: Approved welcome communication | D13: VA drafts | E13: Not started | F13: Missing contact preference | G13: Approved communication sent and recorded.
A14: ONB-10 | B14: Handover / closure | C14: Handover note and outstanding items | D14: VA | E14: Not started | F14: Any open task remains | G14: Owner, next action, follow-up and closure condition recorded.

Sheet M10_Agreement
A1: M10 — Fictional Service Agreement Draft
A2: FICTIONAL TRAINING DOCUMENT — NOT A LEGAL AGREEMENT. VA prepares/tracks; authorized person reviews and approves.
A4: Section | B4: Draft Field | C4: Example / Prompt | D4: Learner Entry | E4: Review Owner
A5: Parties | B5: Participant | C5: Grace Mitchell / P09 (fictional) | E5: Authorized provider representative
A6: Parties | B6: Provider | C6: Wattlebird Support Services (fictional) | E6: Authorized provider representative
A7: Term | B7: Start date | C7: Enter fictional agreed date | E7: Manager
A8: Term | B8: End date | C8: Enter fictional agreed date | E8: Manager
A9: Supports | B9: Support requested | C9: Community access — draft only | E9: Support coordinator
A10: Schedule | B10: Proposed schedule | C10: Enter proposed days/times; verify availability | E10: Operations/coordination
A11: Pricing | B11: Training price reference | C11: Use manager/finance-supplied fictional figure only; learner does not determine the rate. | D11: For manager | E11: Manager/finance
A12: Cancellations | B12: Provider procedure | C12: State 'subject to current provider procedure and applicable rules' rather than inventing legal terms | E12: Manager
A13: Privacy | B13: Information handling | C13: Provider-authorized systems and approved workflows only | E13: Manager/privacy owner
A14: Review | B14: Status | C14: DRAFT — FOR MANAGER REVIEW | E14: Manager
A15: Closure | B15: Final approval | C15: Record approval/version/date only after authorized review | E15: Manager

Sheet M14_Systems_ReadMe
A1: M14 — Wattlebird Systems Lab
A2: Fictional interfaces. No government branding, no real credentials, no real participant data.
A4: Lab ID | B4: Task | C4: System Area | D4: Learner Action | E4: Evidence | F4: Boundary
A5: SYS-01 | B5: Find participant record | C5: Participant Registry | D5: Locate P08 and confirm site, management type and agreement status. | E5: Record fields in learner worksheet. | F5: Use fictional data only.
A6: SYS-02 | B6: Check worker status | C6: Staff & Compliance | D6: Find W08 and identify the screening status shown in the fictional system. | E6: Record status and affected roster shift. | F6: Do not infer legal eligibility beyond the fictional system/provider instruction.
A7: SYS-03 | B7: Check booking | C7: Bookings | D7: Find BK-104 and identify participant, worker, date/time and status. | E7: Record booking details. | F7: Do not change a booking without authorization.
A8: SYS-04 | B8: Review claim | C8: Claims | D8: Find CLM-203 and compare item, quantity, rate and participant context. | E8: Complete a check note. | F8: Do not approve or submit claims independently.
A9: SYS-05 | B9: Log incident | C9: Incident Register | D9: Open IR-008 and draft a factual update/handoff. | E9: Draft update only. | F9: Do not decide reportability.
A10: SYS-06 | B10: Credential safety | C10: Access | D10: Respond to a request to use a supervisor's login. | E10: Document safe response. | F10: Never use or store another person's credentials.

Sheet M14_Participants
A1: M14 Systems Lab — Participant Registry
A2: FICTIONAL SCREEN.
A4: Record ID | B4: Participant | C4: Site | D4: Management Type | E4: Agreement | F4: Plan Review | G4: Notes
A5: REC-P08 | B5: Ben Taylor | C5: Gold Coast | D5: Plan-managed | E5: Signed | F5: 18/03/2027 | G5: Fictional record
A6: REC-P09 | B6: Grace Mitchell | C6: Melbourne | D6: To be confirmed | E6: Not started | F6: — | G6: New referral; owner review required
A7: REC-P12 | B7: Ravi Patel | C7: Melbourne | D7: Plan-managed | E7: Signed | F7: 26/02/2027 | G7: Approx. remaining fictional funds: AUD 420

Sheet M14_Staff
A1: M14 Systems Lab — Staff & Compliance
A2: FICTIONAL SCREEN. Not a government database.
A4: Record ID | B4: Worker | C4: Site | D4: Role | E4: Screening Status | F4: Expiry | G4: Eligible to Work (Fictional Field)
A5: REC-W03 | B5: Sophie Lam | C5: Melbourne | D5: Support worker | E5: Clearance | F5: 30/08/2027 | G5: Yes
A6: REC-W08 | B6: Noah Kelly | C6: Gold Coast | D6: Support worker | E6: Expired | F6: 25/10/2026 | G6: No
A7: REC-W07 | B7: Isla Barrett | C7: Gold Coast | D7: Support worker | E7: Clearance | F7: 09/09/2027 | G7: Yes
A8: REC-A02 | B8: Peter Lindqvist | C8: Melbourne | D8: Physiotherapist | E8: Check provider requirement | F8: — | G8: —

Sheet M14_Bookings
A1: M14 Systems Lab — Booking Register
A2: FICTIONAL SCREEN. Dates/times are practice values.
A4: Booking ID | B4: Participant ID | C4: Worker ID | D4: Date | E4: Start | F4: End | G4: Site | H4: Status
A5: BK-101 | B5: P08 | C5: W07 | D5: 46329 | E5: 0.375 | F5: 0.5 | G5: Gold Coast | H5: Confirmed
A6: BK-102 | B6: P12 | C6: A02 | D6: 46330 | E6: 0.54166667 | F6: 0.625 | G6: Melbourne | H6: Confirmed
A7: BK-103 | B7: P02 | C7: W05 | D7: 46330 | E7: 0.41666667 | F7: 0.58333333 | G7: Melbourne | H7: Confirmed
A8: BK-104 | B8: P06 | C8: W03 | D8: 46328 | E8: 0.5 | F8: 0.66666667 | G8: Melbourne | H8: Confirmed

Sheet M14_Claims
A1: M14 Systems Lab — Claims Register
A2: FICTIONAL SCREEN. Claim values are invented and checked against fictional Wattlebird data.
A4: Claim ID | B4: Participant ID | C4: Management Type | D4: Item Code | E4: Qty | F4: Rate | G4: Total | H4: Status
A5: CLM-201 | B5: P01 | C5: Plan-managed | D5: FX-CA-WD | E5: 2 | F5: 62 | G5: =E5*F5 -> 124 | H5: Ready
A6: CLM-202 | B6: P02 | C6: Self-managed | D6: FX-DL-WD | E6: 4 | F6: 68 | G6: =E6*F6 -> 272 | H6: Review
A7: CLM-203 | B7: P12 | C7: Plan-managed | D7: FX-PT-01 | E7: 1 | F7: 190 | G7: =E7*F7 -> 190 | H7: Review
A8: CLM-204 | B8: P07 | C8: Plan-managed | D8: FX-PS-01 | E8: 1 | F8: 220 | G8: =E8*F8 -> 220 | H8: Ready

Sheet M14_Incidents
A1: M14 Systems Lab — Incident Register
A2: FICTIONAL SCREEN. Record facts and hand off; the VA does not determine reportability.
A4: Incident ID | B4: Participant ID | C4: Reported Date/Time | D4: Reported Facts | E4: Immediate Action | F4: Escalated To | G4: Status
A5: IR-010 | B5: P05 | C5: 06/11/2026 11:10 | D5: Participant reported a minor fall with no ambulance response recorded in the message. | E5: Recorded factual report; urgent owner review required. | F5: Rhonda Blake | G5: Open
A6: IR-008 | B6: P11 | C6: 07/11/2026 14:15 (event time not documented; reported as earlier that morning) | D6: Worker reported participant fall; ambulance called. Event time was not documented in the source message. | E6: Participant taken for medical care. | F6: Rhonda Blake | G6: Urgent
A7: IR-009 | B7: P01 | C7: 02/11/2026 12:20 | D7: Roster containing Marisol information was sent to Priya email by mistake. | E7: Record facts and prepare privacy/operations handoff. | F7: Rhonda Blake | G7: Open

Sheet M14_SOP_Task
A1: M14 — SOP Prove Task
A2: FICTIONAL TRAINING TEMPLATE. Use the canonical workflow and Wattlebird procedure; do not invent legal or clinical steps.
A4: SOP Section | B4: Learner Requirement | C4: Prompt | D4: Learner Entry
A5: Purpose | B5: State what the task achieves. | C5: Example: checking a fictional claim before manager review.
A6: Trigger | B6: When does the task start? | C6: Example: a claim is received for review.
A7: Inputs | B7: What records are needed? | C7: Participant record, claim record, fictional price table.
A8: Steps | B8: Write numbered steps. | C8: Find record → check fields → classify → record note → hand off if needed → follow up.
A9: Escalation | B9: When does the VA stop and hand off? | C9: Authority, safety/privacy/compliance issue, or decision outside VA role.
A10: Follow-up | B10: How is the task tracked? | C10: Owner, next action, trigger/date, response, closure condition.
A11: Closure | B11: What proves the task is complete? | C11: Manager disposition recorded and relevant record/task updated.

Sheet M15_Capstone
A1: M15 — Wattlebird Mixed Workweek Capstone
A2: Independent mixed-workweek assessment: Mon 2–Sun 8 Nov 2026. The capstone uses newly instantiated assessment inputs; several tasks deliberately test skills practised earlier in new combinations.
A3: Task ID | B3: Day | C3: Incoming Work | D3: Learner Priority | E3: Learner Classification | F3: Evidence / Notes | G3: Owner / Handoff | H3: Follow-Up | I3: Closure Condition | J3: Source Check Required?
A4: CAP-01 | B4: Mon 2 Nov | C4: Worker W07 reports they cannot cover P08's 1:00–4:00 pm Gold Coast support shift today. | J4: No
A5: CAP-02 | B5: Tue 3 Nov | C5: A draft roster shows W10 assigned to two Melbourne participants during overlapping hours. | J5: No
A6: CAP-03 | B6: Tue 3 Nov | C6: A new referral asks whether NDIS funding can be used for a proposed community-transport support. | J6: No
A7: CAP-04 | B7: Tue 3 Nov | C7: Participant P12 asks whether their Melbourne support scheduled for Sun 8 Nov is affected by a Victorian public holiday. | J7: Yes
A8: CAP-05 | B8: Wed 4 Nov | C8: A fresh six-line invoice mini-batch contains mixed OK / FLAG / ASK cases. | J8: No
A9: CAP-06 | B9: Wed 4 Nov | C9: A worker reports that a participant progress note was emailed to an unrelated external address. | J9: No
A10: CAP-07 | B10: Thu 5 Nov | C10: Operations asks for a draft review of participant P04’s service agreement because a review meeting has been scheduled. | J10: No
A11: CAP-08 | B11: Thu 5 Nov | C11: Participant P10 asks whether a future support-coordination booking can proceed because fictional Capacity Building funds are nearly used. | J11: No
A12: CAP-09 | B12: Sat 7 Nov | C12: A worker reports an incident involving participant P02. Report received at 6:40 pm; incident happened earlier that evening and ambulance assistance was requested. | J12: No
A13: CAP-10 | B13: Sun 8 Nov | C13: Operations asks for an audit-preparation gap check across the fixed complaint and incident records supplied for the capstone. | J13: No
A16: Required capstone outputs
A17: 1. Completed task evidence
A18: 2. Follow-Up/Handover Log
A19: 3. One current-source check entry
A20: 4. End-of-week handover note
A21: 5. Portfolio-ready filenames and fictional labels
A23: Capstone scoring
A24: Capstone pass condition: at least 16/20 points and no Critical Failure. Certification also requires the separate Certification Rubric threshold and required-criterion rules.

Sheet M16_Portfolio
A1: M16 — Portfolio Assembly
A2: Keep full certification evidence separately from a smaller client-facing showcase. Label all practice work honestly.
A4: Folder / Binder | B4: Minimum Contents | C4: Naming Pattern | D4: Required Label | E4: Purpose
A5: 01_Workplace_Foundations | B5: M1 profile, M2 workplace messages, M3 file structure, M4 handover | C5: 01_M1_Profile_v1 | D5: FICTIONAL TRAINING ARTIFACT — CREATED FOR PRACTICE PURPOSES ONLY | E5: Shows workplace readiness.
A6: 02_NDIS_Admin | B6: M5 glossary, M6 plan exercise, M7 role triage, M8 source check | C6: 02_M6_PlanBreakdown_v1 | D6: FICTIONAL TRAINING ARTIFACT — CREATED FOR PRACTICE PURPOSES ONLY | E6: Shows NDIS admin reasoning.
A7: 03_Operations | B7: M9 roster, M10 onboarding/agreement, M11 invoice log | C7: 03_M9_RosterCheck_v1 | D7: FICTIONAL TRAINING ARTIFACT — CREATED FOR PRACTICE PURPOSES ONLY | E7: Shows operational accuracy.
A8: 04_Privacy_Compliance | B8: M12 privacy response, M13 incident/complaint work, M14 SOP | C8: 04_M12_PrivacyResponse_v1 | D8: FICTIONAL TRAINING ARTIFACT — CREATED FOR PRACTICE PURPOSES ONLY | E8: Shows boundaries and escalation.
A9: 05_Capstone | B9: M15 mixed week, follow-up log, handover, source log | C9: 05_M15_Capstone_v1 | D9: FICTIONAL TRAINING ARTIFACT — CREATED FOR PRACTICE PURPOSES ONLY | E9: Shows integrated execution.
A10: 06_Job_Readiness | B10: M16 profile/cover letter, M17 30-day plan/trial task | C10: 06_Profile_v1 | D10: FICTIONAL TRAINING ARTIFACT — CREATED FOR PRACTICE PURPOSES ONLY | E10: Shows job application readiness.
A13: Client showcase | B13: Select 5–6 polished pieces from certification evidence; keep complete evidence available for assessment.

Sheet Certification_Rubric
A1: Certification Rubric — v2.2
A2: 10 criteria × 0–2 = 20 points. Pass: 16/20 or higher, with every Required criterion at least 1.
A4: # | B4: Criterion | C4: Required? | D4: 0 — Not demonstrated / unsafe | E4: 1 — Partial | F4: 2 — Demonstrated
A5: 1 | B5: Administrative Accuracy | C5: Yes | D5: Materially incorrect records, roster/invoice errors, or unsafe checking. | E5: Minor errors; core work partly correct after review. | F5: Accurate records, checks and outputs with no material avoidable errors.
A6: 2 | B6: NDIS Accuracy / Appropriate Verification | C6: Yes | D6: Incorrect current claim or confident unsupported statement. | E6: Correct general approach but verification/source logging is incomplete. | F6: Uses current official sources when needed and clearly labels uncertainty.
A7: 3 | B7: Communication | C7: Yes | D7: Unclear, misleading, or inappropriate message. | E7: Understandable but needs editing or stronger ownership. | F7: Clear, professional, concise, appropriately directed.
A8: 4 | B8: Organization | C8: Yes | D8: Work cannot be followed or key evidence is missing. | E8: Basic organization with gaps. | F8: Logical folders, naming, task tracking and version control.
A9: 5 | B9: Privacy / Fictional Data Handling | C9: Yes | D9: Uses/discloses information unsafely or treats fictional data as real. | E9: Recognizes privacy issue but response needs correction. | F9: Uses fictional data safely and follows provider-authorized workflow principles.
A10: 6 | B10: Boundary Judgment | C10: Yes | D10: Makes clinical, legal, funding, approval or provider decisions outside role. | E10: Recognizes some boundaries but needs prompting. | F10: Consistently gathers, drafts, checks, asks and hands off within role.
A11: 7 | B11: Escalation Judgment | C11: Yes | D11: Fails to escalate a safety/privacy/compliance/authority issue. | E11: Escalates but channel/owner/timing needs correction. | F11: Identifies owner, channel, urgency, handoff and follow-up appropriately.
A12: 8 | B12: Follow-Up / Closure | C12: Yes | D12: Leaves open work untracked or marks closure without evidence. | E12: Tracks some follow-up but misses owner/trigger/closure detail. | F12: Clearly records outstanding item, owner, next action, trigger, response and closure.
A13: 9 | B13: Documentation | C13: Yes | D13: Facts are missing, judgment is presented as fact, or logs are incomplete. | E13: Mostly factual but needs structure/detail. | F13: Neutral, factual, complete and traceable documentation.
A14: 10 | B14: Portfolio Completeness / Honest Representation | C14: Yes | D14: Missing required evidence or claims real client/NDIS certification experience inaccurately. | E14: Evidence mostly complete with labeling/organization gaps. | F14: Complete required evidence, clearly fictional, professionally presented.
A17: Pass rule | B17: 16/20 or higher AND every Required criterion scores at least 1.
A18: Remediation | B18: Any 0 on a Required criterion blocks certification until corrected and reassessed. Safety/privacy/boundary failures require remediation.
A19: Calibration | B19: 16/20 is 80%; it demonstrates consistent beginner competence while the required-criterion floor prevents unsafe gaps from being averaged away.
A20: Human review | B20: Final certification is human-reviewed when current-law, privacy, safety, or ambiguous judgment issues arise.

Sheet M11_Service_Delivery
A1: M11 — Fictional Service-Delivery Evidence
A2: FICTIONAL TRAINING DATA. Use to check whether invoiced services have matching delivery evidence.
A3: Delivery ID | B3: Service Date | C3: Participant ID | D3: Participant Name | E3: Item Code | F3: Worker ID | G3: Start | H3: End | I3: Delivered Qty | J3: Status | K3: Evidence Note
A4: SD-001 | B4: 46321 | C4: P01 | D4: =IFERROR(INDEX(Participants!$B$4:$B$15,MATCH(C4,Participants!$A$4:$A$15,0)),"NOT FOUND") -> Marisol Reyes | E4: FX-CA-WD | F4: W01 | G4: 09:00 | H4: 11:00 | I4: 2 | J4: Delivered | K4: Fictional delivery record linked to INV-1001.
A5: SD-002 | B5: 46321 | C5: P04 | D5: =IFERROR(INDEX(Participants!$B$4:$B$15,MATCH(C5,Participants!$A$4:$A$15,0)),"NOT FOUND") -> Tom Nguyen | E5: FX-DL-WD | F5: W10 | G5: 09:00 | H5: 13:00 | I5: 4 | J5: Delivered | K5: Fictional delivery record linked to INV-1002.
A6: SD-003 | B6: 46322 | C6: P06 | D6: =IFERROR(INDEX(Participants!$B$4:$B$15,MATCH(C6,Participants!$A$4:$A$15,0)),"NOT FOUND") -> Jack O'Connor | E6: FX-DL-WD | F6: W06 | G6: 09:00 | H6: 13:00 | I6: 4 | J6: Delivered | K6: Fictional delivery record linked to INV-1003.
A7: SD-005 | B7: 46323 | C7: P02 | D7: =IFERROR(INDEX(Participants!$B$4:$B$15,MATCH(C7,Participants!$A$4:$A$15,0)),"NOT FOUND") -> Daniel Whitfield | E7: FX-DL-WD | F7: W10 | G7: 10:00 | H7: 14:00 | I7: 4 | J7: Delivered | K7: Fictional delivery record linked to INV-1005.
A8: SD-006 | B8: 46323 | C8: P12 | D8: =IFERROR(INDEX(Participants!$B$4:$B$15,MATCH(C8,Participants!$A$4:$A$15,0)),"NOT FOUND") -> Ravi Patel | E8: FX-PT-01 | F8: A02 | G8: 13:00 | H8: 14:00 | I8: 1 | J8: Delivered | K8: Fictional delivery record linked to INV-1006.
A9: SD-007 | B9: 46323 | C9: P07 | D9: =IFERROR(INDEX(Participants!$B$4:$B$15,MATCH(C9,Participants!$A$4:$A$15,0)),"NOT FOUND") -> Lucia Fernandez | E9: FX-PS-01 | F9: A03 | G9: 10:00 | H9: 11:00 | I9: 1 | J9: Delivered | K9: Fictional delivery record linked to INV-1007.
A10: SD-008 | B10: 46324 | C10: P04 | D10: =IFERROR(INDEX(Participants!$B$4:$B$15,MATCH(C10,Participants!$A$4:$A$15,0)),"NOT FOUND") -> Tom Nguyen | E10: FX-OT-01 | F10: A01 | G10: 09:00 | H10: 10:00 | I10: 1 | J10: Delivered | K10: Fictional delivery record linked to INV-1008.
A11: SD-009 | B11: 46324 | C11: P08 | D11: =IFERROR(INDEX(Participants!$B$4:$B$15,MATCH(C11,Participants!$A$4:$A$15,0)),"NOT FOUND") -> Ben Taylor | E11: FX-CA-WD | F11: W07 | G11: 09:00 | H11: 13:00 | I11: 4 | J11: Delivered | K11: Fictional delivery record linked to INV-1009.
A12: SD-010 | B12: 46324 | C12: P03 | D12: =IFERROR(INDEX(Participants!$B$4:$B$15,MATCH(C12,Participants!$A$4:$A$15,0)),"NOT FOUND") -> Aisha Rahman | E12: FX-SC-01 | F12: S03 | G12: 09:00 | H12: 11:00 | I12: 2 | J12: Delivered | K12: Fictional delivery record linked to INV-1010.
A13: SD-011 | B13: 46325 | C13: P11 | D13: =IFERROR(INDEX(Participants!$B$4:$B$15,MATCH(C13,Participants!$A$4:$A$15,0)),"NOT FOUND") -> Hannah Kowalski | E13: FX-DL-WD | F13: W09 | G13: 09:00 | H13: 13:00 | I13: 4 | J13: Delivered | K13: Fictional delivery record linked to INV-1011.
A14: SD-012 | B14: 46325 | C14: P06 | D14: =IFERROR(INDEX(Participants!$B$4:$B$15,MATCH(C14,Participants!$A$4:$A$15,0)),"NOT FOUND") -> Jack O'Connor | E14: FX-DL-WE | F14: W06 | G14: 17:00 | H14: 20:00 | I14: 3 | J14: Delivered | K14: Fictional delivery record linked to INV-1012; weekday evening window.
A15: SD-013 | B15: 46325 | C15: P12 | D15: =IFERROR(INDEX(Participants!$B$4:$B$15,MATCH(C15,Participants!$A$4:$A$15,0)),"NOT FOUND") -> Ravi Patel | E15: FX-DL-WD | F15: W10 | G15: 14:00 | H15: 18:00 | I15: 4 | J15: Delivered | K15: Fictional delivery record linked to INV-1013.
... A19: SD-017 | B19: 46324 | C19: P05 | D19: =IFERROR(INDEX(Participants!$B$4:$B$15,MATCH(C19,Participants!$A$4:$A$15,0)),"NOT FOUND") -> Priya Nair | E19: FX-CA-WD | F19: W11 | G19: 09:00 | H19: 12:00 | I19: 3 | J19: Delivered | K19: Fictional delivery record linked to INV-1020.

Sheet M1_Job_Post
A1: M1 — Fictional Wattlebird VA Job Post
A2: FICTIONAL JOB POST — training use only.
A3: Field | B3: Detail
A4: Role | B4: Part-time Virtual Assistant — Wattlebird Support Services
A5: Reports to | B5: Rhonda Blake, Operations Manager
A6: Core tasks | B6: Inbox administration, roster checks, document tracking, invoice pre-checks, follow-up and handover
A7: Systems | B7: Google Workspace, Wattlebird practice spreadsheets, free task board/chat
A8: Communication | B8: Clear, factual, timely; acknowledge receipt and give the next expected update when appropriate
A9: Boundaries | B9: Do not make clinical, funding, legal, reportability, approval or worker-eligibility decisions
A10: Security | B10: Use provider-authorized systems and follow provider security procedures
A11: Practice note | B11: Applicants should describe simulated Wattlebird work honestly as fictional practice

Sheet M1_Profile_Template
A1: M1 — VA Profile Template
A2: Learner template. Describe practice honestly.
A3: Field | B3: Learner Entry
A4: Role statement
A5: Relevant skills
A6: Wattlebird practice completed
A7: Systems practiced
A8: What I have not used professionally
A9: Availability
A10: Communication approach
A11: Portfolio evidence

Sheet M2_Weak_Drafts
A1: M2 — Weak Message Drafts
A2: FICTIONAL drafts for rewriting practice.
A3: Draft ID | B3: Context | C3: Weak Draft | D3: Learner Rewrite
A4: WD-01 | B4: Roster clash | C4: There is a problem with the roster.
A5: WD-02 | B5: Invoice question | C5: Please check this.
A6: WD-03 | B6: Follow-up | C6: Any update?
A7: WD-04 | B7: Sent Mon 2 Nov, 11:45 am (Melbourne) to Jamal Ortiz; attached InvoiceCheck_v1 instead of v2. | C7: I accidentally attached an outdated fictional invoice-check file to an internal email.

Sheet M2_Incomplete_Questions
A1: M2 — Incomplete Workplace Questions
A2: FICTIONAL prompts for turning vague questions into actionable requests.
A3: Question ID | B3: Context | C3: Incomplete Question | D3: Learner Rewrite
A4: IQ-01 | B4: Roster | C4: Can someone cover?
A5: IQ-02 | B5: Invoice | C5: Is this okay?
A6: IQ-03 | B6: Agreement | C6: What about Lucia?
A7: IQ-04 | B7: Privacy | C7: What should I do?
A8: IQ-05 | B8: Funding | C8: Can we book it?

Sheet M3_Messy_Files
A1: M3 — Messy File Naming Practice
A2: FICTIONAL filenames. Learner proposes a consistent naming pattern.
A3: File ID | B3: Current Filename | C3: Learner New Filename | D3: Reason
A4: MF-01 | B4: final-final roster.xlsx
A5: MF-02 | B5: Invoice new 2.xlsx
A6: MF-03 | B6: Grace agreement latest.docx
A7: MF-04 | B7: handover.docx
A8: MF-05 | B8: source check updated.xlsx

Sheet M4_Format_Trap
A1: M4 — Date and Format Trap
A2: FICTIONAL practice examples. Use the stated Wattlebird format and verify ambiguous dates.
A3: Item ID | B3: Displayed Value | C3: Issue to Check | D3: Learner Correction / Note
A4: DF-01 | B4: 04/11/2026 | C4: Could mean 4 Nov or 11 Apr depending on convention.
A5: DF-02 | B5: 11/04/2026 | C5: Could mean 11 Apr or 4 Nov depending on convention.
A6: DF-03 | B6: AUD 205 | C6: Confirm this is fictional currency formatting, not a real price claim.
A7: DF-04 | B7: 2026-11-03 | C7: ISO-style date; identify the corresponding local day.

Sheet M4_Handover_Template
A1: M4 — Handover Note Template
A2: Learner template. State facts, owner, next action, follow-up and closure.
A3: Field | B3: Learner Entry
A4: Date/time
A5: Task / issue
A6: What happened
A7: Current status
A8: Owner
A9: Next action
A10: Channel
A11: Follow-up trigger
A12: Closure condition
A13: Requester/affected party informed?

Sheet M5_Situations
A1: M5 — Organization and Role Matching
A2: FICTIONAL situations. Match each to the most appropriate role/owner.
A3: Situation ID | B3: Situation | C3: Learner Role/Owner | D3: Reason
A4: SIT-01 | B4: Participant asks what NDIS funding covers.
A5: SIT-02 | B5: Invoice batch needs administrative pre-check.
A6: SIT-03 | B6: Participant asks for copies of records.
A7: SIT-04 | B7: Worker reports a participant injury.
A8: SIT-05 | B8: Agreement draft needs approval.

Sheet M5_Safe_Questions
A1: M5 — Safe Question Practice
A2: FICTIONAL prompts. Draft a safe acknowledgment, clarification and handoff.
A3: Prompt ID | B3: Question Type | C3: Prompt | D3: Learner Response
A4: SQ-01 | B4: Funding | C4: Does NDIS fund this new support?
A5: SQ-02 | B5: Clinical suitability | C5: Would this support be clinically suitable for the participant?
A6: SQ-03 | B6: Eligibility | C6: Is this participant eligible for this support?

Sheet M8_Pricing_Check_Log
A1: M8 — Learner Pricing Check Log
A2: Use current official sources for real-world information. Wattlebird prices are fictional.
A3: Check ID | B3: Support Item / Code | C3: Official Source | D3: Date Checked | E3: Version / Effective Date | F3: Unit | G3: Applicability / Management Type | H3: Finding | I3: Action / Owner

Sheet M9_Extended_Practice
A1: M9 — Extended Roster Practice
A2: FICTIONAL cases. Propose options; the authorized owner decides.
A3: Case ID | B3: Scenario | C3: Evidence | D3: Learner Priority | E3: Learner Classification | F3: Options / Next Action | G3: Owner | H3: Follow-Up | I3: Closure
A4: M9-X1 | B4: Approved leave conflicts with a scheduled shift | C4: W05 unavailable 4–5 Nov; BK-103 shows a 4 Nov booking. | G4: Operations manager
A5: M9-X2 | B5: Shift is unfilled | C5: R12 has no confirmed worker. Suggest two feasible options. | G5: Operations manager
A6: M9-X3 | B6: Timezone label error | C6: Gold Coast booking is entered with AEDT instead of AEST. | G6: Operations manager

Sheet M12_Security_Practice
A1: M12 — Provider-Policy Security Practice
A2: FICTIONAL. Follow Wattlebird/provider policy; do not invent universal technical rules.
A3: Case ID | B3: Scenario | C3: Learner Action | D3: Classification | E3: Follow-Up
A4: SP-01 | B4: A VA is asked to work from public Wi-Fi with participant information.
A5: SP-02 | B5: A family computer is used for provider work and security expectations are unclear.
A6: SP-03 | B6: A staff member asks you to forward participant data to a personal email.

Sheet M17_Trial_Pack
A1: M17 — Fictional Trial Pack — New Task Instances
A2: FICTIONAL practice. These task instances are newly written for the trial. They test administrative judgment using different record patterns from the worked examples.
A3: Task ID | B3: Input | C3: Learner Work | D3: Expected Output
A4: TR-01 | B4: TR01_Handover_Note: "Follow-up with Olivia completed"; TR01_Follow_Up: owner Olivia, status Open, no closure condition or response recorded. | C4: Compare the handover note with the follow-up record, identify the documentation gap, assign the next action and define what would close it. | D4: Evidence of mismatch, owner/next action, follow-up trigger and closure condition.
A5: TR-02 | B5: TR02_Invoice_Line: INV-TR02 / P04 / 05-Nov-2026 / item FX-XX-77 / qty 1 / rate 75. The item code is absent from Price_Table. | C5: Identify the exception, ask/route it to the appropriate owner and define the closure condition. | D5: Exception record, clarification route and closure condition.
A6: TR-03 | B6: TR03_Task_Board: TASK-TR03 requests record MISSING-REC-01 from M14_Bookings; no such record is supplied in that sheet. | C6: Verify the requested source, document what is missing, avoid inventing the record and prepare a factual handoff. | D6: Evidence checked, missing-record note, owner/handoff and follow-up condition.

Sheet M17_30_Day_Plan
A1: M17 — First 30 Days Plan
A2: Learner template for an honest first-month onboarding conversation.
A3: Question / Topic | B3: Learner Notes
A4: Systems and access
A5: SOPs and provider procedures
A6: Escalation contacts and backup
A7: After-hours procedure
A8: Expected response hours
A9: Privacy/security requirements
A10: Current-source expectations
A11: Communication channels
A12: Review/check-in cadence
A13: Training gaps

Sheet M16_Outreach_Template
A1: M16 — Honest Outreach Template
A2: Learner template. Describe fictional practice accurately; do not claim client employment.
A3: Field | B3: Learner Draft
A4: Subject
A5: Opening
A6: Relevant VA skills
A7: Relevant fictional practice
A8: Systems practiced honestly
A9: Availability
A10: Portfolio link/label
A11: Closing

Sheet Calibration_Exemplars
A1: Certification Calibration Exemplars
A2: Fictional examples for self-audit. These are calibration examples, not answer keys to the capstone.
A3: # | B3: Criterion | C3: 0 Example | D3: 1 Example | E3: 2 Example
A4: 1 | B4: Administrative Accuracy | C4: Example: changes an invoice quantity in the source workbook instead of recording the discrepancy for review. | D4: Example: checks most fields but misses one discrepancy or needs correction. | E4: Example: complete, traceable check with correct evidence and no invented changes.
A5: 2 | B5: NDIS Accuracy / Appropriate Verification | C5: Example: treats a fictional Wattlebird price as a universal NDIS rule without checking the current official source. | D5: Example: identifies the need to verify but omits source/version detail. | E5: Example: correctly distinguishes fictional Wattlebird rules from current NDIS requirements and documents verification.
A6: 3 | B6: Communication | C6: Example: sends a vague message such as “There is a problem” with no record, owner, requested action or next step. | D6: Example: message is understandable but misses timing or owner. | E6: Example: concise, factual message that another person can act on without clarification.
A7: 4 | B7: Organization | C7: Example: saves practice evidence under an unclear filename and cannot identify which scenario it came from. | D7: Example: evidence exists but requires cleanup or reorganization. | E7: Example: evidence is traceable by scenario/ID and easy for another person to locate.
A8: 5 | B8: Privacy / Fictional Data Handling | C8: Example: copies fictional participant information into an unauthorized channel or invents missing personal information. | D8: Example: mostly safe but one handling step needs correction. | E8: Example: clearly preserves fictional-data boundaries and follows approved handling/urgent handoff rules.
A9: 6 | B9: Boundary Judgment | C9: Example: approves, rejects, negotiates or changes an invoice even though the provider workflow assigns that decision to an owner. | D9: Example: mostly stays in role but wording suggests an unauthorized decision. | E9: Example: consistently separates administrative checking from authorized decisions.
A10: 7 | B10: Escalation Judgment | C10: Example: ignores an urgent privacy issue or sends the handoff without identifying the owner or acknowledgement path. | D10: Example: correct escalation but missing timing/acknowledgement. | E10: Example: correct owner, channel, urgency, acknowledgement and follow-up path.
A11: 8 | B11: Follow-Up / Closure | C11: Example: marks an issue closed immediately after sending a message, without a response or closure evidence. | D11: Example: tracks the item but closure evidence is vague. | E11: Example: records trigger, owner and evidence required for closure; no-response remains open.
A12: 9 | B12: Documentation | C12: Example: writes “handled” without recording what was checked, what was found or what remains open. | D12: Example: adequate note with minor traceability gap. | E12: Example: another person can take over from the note without asking what happened.
A13: 10 | B13: Portfolio Completeness / Honest Representation | C13: Example: presents fictional practice work as real client experience or claims responsibility for decisions made by the provider. | D13: Example: portfolio item is usable but overstates responsibility. | E13: Example: artifact is labeled fictional/practice where appropriate and accurately describes the learner’s contribution.

Sheet Self_Audit_Guide
A1: Certification Self-Audit Guide
A2: Use after completing required evidence. Final certification threshold: 16/20; every Required criterion at least 1; any Required 0 blocks certification.
A3: Criterion | B3: Evidence to Review | C3: Self-Check Question | D3: Score (0–2) | E3: Remediation Needed?
A4: Administrative Accuracy | B4: M11_Invoice_Check_Log + relevant invoice/service-delivery rows | C4: Can another person verify the key facts from the evidence without asking me to reconstruct the work?
A5: NDIS Accuracy / Appropriate Verification | B5: `M8_Pricing_Check_Log` + any current-source lesson evidence | C5: Did I use the correct current source for any real-world NDIS claim, and did I keep fictional Wattlebird rules separate?
A6: Communication | B6: M2 message drafts / M2_Weak_Drafts completed work | C6: Could the recipient act from my message without a second clarification?
A7: Organization | B7: M16_Portfolio folders + scenario-ID filenames | C7: Can I locate each required evidence item quickly and trace it to its scenario or task?
A8: Privacy / Fictional Data Handling | B8: M12_Security_Practice + Security_Extensions + E07/SEC-02 handoff evidence | C8: Did I keep all practice data fictional and follow the provider-approved handling procedure?
A9: Boundary Judgment | B9: M2 Work Boundary evidence + M11_Invoice_Check_Log | C9: Did I stay within the VA role and leave approval/funding/clinical/authorization decisions with the owner?
A10: Escalation Judgment | B10: M2.3 urgent escalation + Follow_Up_Log where applicable | C10: Did I choose the correct owner and use the defined urgent or routine handoff procedure?
A11: Follow-Up / Closure | B11: Follow_Up_Log entries + closure evidence | C11: Did I record the trigger and the evidence that would prove closure?
A12: Documentation | B12: Completed task notes / handover evidence | C12: Could another person take over from my notes without asking what happened?
A13: Portfolio Completeness / Honest Representation | B13: M16_Portfolio descriptions and fictional-training labels | C13: Does my portfolio accurately describe what I personally did and clearly label fictional practice evidence?

Sheet M11_Invoice_Check_Log
A1: M11 — Learner Invoice Check Log
A2: Blank learner template. Check each line against evidence; record unit, route-to and follow-up. Fictional prices only.
A3: Invoice # | B3: Participant | C3: Service Date | D3: Item | E3: Qty | F3: Unit | G3: Fictional Rate/Reference | H3: Management Type | I3: Duplicate Check | J3: Service-Delivery Evidence | K3: Route To | L3: Classification | M3: Why / Evidence | N3: Follow-Up / Closure

Sheet M6_Support_Requests
A1: M6 — Fictional Support Requests
A2: Use only with M6_Fictional_Plan. Identify what is known, what is ambiguous, and what requires an authorized answer.
A3: Request ID | B3: Request | C3: Known Plan Context | D3: Learner Category / Match | E3: What Is Unclear? | F3: Clarification Question
A4: SR-01 | B4: Weekly community access support | C4: Core allocation exists
A5: SR-02 | B5: Physiotherapy appointment | C5: Capacity Building allocation exists
A6: SR-03 | B6: New support request with unclear category | C6: Plan has Core and Capacity Building allocations

Sheet M15_Capstone_Scenarios
A1: M15 — Fresh Capstone Scenario Pack
A2: FICTIONAL TRAINING DATA. These are assessment inputs created for M15 and are not copied from the worked scenarios in Modules 1–14.
A3: Task ID | B3: Day | C3: Incoming Work | D3: Supporting Evidence / Starting Point | E3: Source Check? | F3: Exercise Note
A4: CAP-01 | B4: Mon 2 Nov | C4: Worker W07 reports they cannot cover P08's 1:00–4:00 pm Gold Coast support shift today. | D4: Use M15_Capstone_Roster CRO-01 and the CAP-01 candidate extract in that sheet; verify site, availability and screening before proposing cover. | E4: No | F4: Use the supplied screening, site and availability facts; do not choose the final cover.
A5: CAP-02 | B5: Tue 3 Nov | C5: A draft roster shows W10 assigned to two Melbourne participants during overlapping hours. | D5: Use M15_Capstone_Roster CRO-02 and CRO-03; verify the overlap before routing. | E5: No | F5: Verify the overlap, identify the affected participants and route the schedule issue.
A6: CAP-03 | B6: Tue 3 Nov | C6: A new referral asks whether NDIS funding can be used for a proposed community-transport support. | D6: Referral question only; no authorized funding answer is provided in the scenario. | E6: No | F6: Do not answer the funding question; identify and use the appropriate authorized owner.
A7: CAP-04 | B7: Tue 3 Nov | C7: Participant P12 asks whether their Melbourne support scheduled for Sun 8 Nov is affected by a Victorian public holiday. | D7: Use Participants for P12/site context and verify the official Victorian 2026 public-holiday source for 8 Nov. | E7: Yes | F7: Record the source result and route any schedule decision to the authorized operations owner.
A8: CAP-05 | B8: Wed 4 Nov | C8: A fresh six-line invoice mini-batch contains mixed OK / FLAG / ASK cases. | D8: Open M15_Capstone_Invoice_Batch and M15_Capstone_Invoice_Evidence; use the M11 checking workflow. | E8: No | F8: Use the supplied fictional rate table and neutral delivery evidence.
A9: CAP-06 | B9: Wed 4 Nov | C9: A worker reports that a participant progress note was emailed to an unrelated external address. | D9: Record only the facts provided in the scenario; use the urgent privacy/operations procedure. | E9: No | F9: Record only the supplied facts and follow the urgent privacy/operations procedure.
A10: CAP-07 | B10: Thu 5 Nov | C10: Operations asks for a draft review of participant P04’s service agreement because a review meeting has been scheduled. | D10: Use Participants for P04 details and copy M10_Agreement before entering capstone data. | E10: No | F10: Prepare and track the draft only; an authorized person reviews and approves terms.
A11: CAP-08 | B11: Thu 5 Nov | C11: Participant P10 asks whether a future support-coordination booking can proceed because fictional Capacity Building funds are nearly used. | D11: Use Participants for P10’s management type, support type and remaining funds; do not use M6_Fictional_Plan. | E11: No | F11: Do not promise a booking; use the participant record and route the funding/booking question.
A12: CAP-09 | B12: Sat 7 Nov | C12: A worker reports an incident involving participant P02. The report is received at 6:40 pm; the incident happened earlier that evening and ambulance assistance was requested. | D12: For this exercise, assume you are covering the Wattlebird inbox at 6:40 pm Saturday. Use the fictional urgent procedure. | E12: No | F12: Record only documented times and follow the urgent procedure; do not invent the incident time.
A13: CAP-10 | B13: Sun 8 Nov | C13: Operations asks for an audit-preparation gap check across the fixed complaint and incident records supplied for the capstone. | D13: Review M15_Capstone_Audit_Records and identify factual/documentation gaps from the raw fields only. | E13: No | F13: Use the raw fields only; distinguish missing documentation from unsupported inference.

Sheet M15_Capstone_Invoice_Batch
A1: M15 — Fresh Fictional Invoice Mini-Batch
A2: FICTIONAL TRAINING DATA. Use only for CAP-05. Rates come from the fictional Price_Table. Delivery evidence is supplied separately in M15_Capstone_Invoice_Evidence.
A3: Invoice ID | B3: Participant ID | C3: Service Date | D3: Item Code | E3: Qty | F3: Rate | G3: Management Type | H3: Evidence ID | I3: Learner Disposition | J3: Learner Notes
A4: CINV-2001 | B4: P03 | C4: 02/11/2026 | D4: FX-DL-WD | E4: 2 | F4: 60 | G4: NDIA-managed | H4: CSD-2001
A5: CINV-2002 | B5: P03 | C5: 02/11/2026 | D5: FX-DL-WD | E5: 2 | F5: 60 | G5: NDIA-managed | H5: CSD-2001
A6: CINV-2003 | B6: P07 | C6: 03/11/2026 | D6: FX-OT-01 | E6: 1 | F6: 190 | G6: Plan-managed
A7: CINV-2004 | B7: P06 | C7: 04/11/2026 | D7: FX-DL-WE | E7: 3 | F7: 66 | G7: NDIA-managed | H7: CSD-2004
A8: CINV-2005 | B8: P08 | C8: 04/11/2026 | D8: FX-CA-WD | E8: 2 | F8: 70 | G8: Plan-managed | H8: CSD-2005
A9: CINV-2006 | B9: P09 | C9: 04/11/2026 | D9: FX-SC-01 | E9: 1 | F9: 100 | H9: CSD-2006

Sheet M15_Capstone_Roster
A1: M15 — Capstone Roster Evidence
A2: FICTIONAL TRAINING DATA. Assessment-only records for CAP-01 and CAP-02. Separate from the practice-week Roster.
A3: Record ID | B3: Date | C3: Participant ID | D3: Participant Site | E3: Start | F3: End | G3: Worker ID | H3: Worker Site | I3: Status | J3: Notes
A4: CRO-01 | B4: 02/11/2026 | C4: P08 | D4: Gold Coast | E4: 13:00 | F4: 16:00 | G4: W07 | H4: Gold Coast | I4: Affected | J4: Assessment roster record for the affected shift.
A5: CRO-02 | B5: 03/11/2026 | C5: P03 | D5: Melbourne | E5: 10:00 | F5: 12:00 | G5: W10 | H5: Melbourne | I5: Draft | J5: Draft roster entry.
A6: CRO-03 | B6: 03/11/2026 | C6: P10 | D6: Melbourne | E6: 11:00 | F6: 13:00 | G6: W10 | H6: Melbourne | I6: Draft | J6: Draft roster entry.
A8: CAP-01 COVER CANDIDATES — FICTIONAL ASSESSMENT EXTRACT (screening status and expiry are supplied facts)
A9: Candidate ID | B9: Name | C9: Role Type | D9: Site | E9: Availability | F9: Screening Status | G9: Screening Expiry
A10: W08 | B10: Noah Kelly | C10: Direct support | D10: Gold Coast | E10: Wed–Sun | F10: EXPIRED | G10: 46320
A11: S04 | B11: Marcus Feld | C11: Non-direct | D11: Gold Coast | E11: Mon–Thu | F11: OK | G11: 46568
A12: W13 | B12: Ava McKenzie | C12: Direct support | D12: Gold Coast | E12: Mon–Fri | F12: OK | G12: 46568

Sheet M15_Capstone_Audit_Records
A1: M15 — Capstone Audit Records
A2: FICTIONAL TRAINING DATA. Raw record fields for CAP-10. Blank fields are intentionally blank; do not infer missing facts.
A3: Record ID | B3: Record Type | C3: Date / Reported | D3: Participant ID | E3: Owner | F3: Status | G3: Complaint / Event Text (verbatim) | H3: Acknowledged Date | I3: Event Date / Time | J3: Containment Action | K3: Owner Response / Closure Note | L3: Source Note
A4: CAR-01 | B4: Complaint | C4: 06/11/2026 | D4: P04 | E4: Operations | F4: Open | G4: Participant reported repeated late arrivals. | L4: Complaint record extract.
A5: CAR-02 | B5: Complaint | C5: 05/11/2026 | D5: P07 | E5: Operations | F5: Closed | G5: Participant raised a concern about communication. | H5: 05/11/2026 | I5: 05/11/2026 10:00 | J5: Follow-up completed. | K5: Operations follow-up completed; participant communication concern addressed. | L5: Complaint record extract.
A6: CAR-03 | B6: Incident | C6: 07/11/2026 | D6: P11 | E6: Rhonda Blake | F6: Urgent | G6: Fall reported; ambulance called; report received at 2:15 pm. | H6: 07/11/2026 | L6: Incident record extract.
A7: CAR-04 | B7: Incident | C7: 02/11/2026 | D7: P01 | E7: Rhonda Blake | F7: Open | G7: Roster information was sent to an unrelated email address. | H7: 02/11/2026 | I7: 02/11/2026 09:30 | L7: Incident record extract.
A8: CAR-05 | B8: Complaint | C8: 04/11/2026 | D8: P03 | E8: Operations | F8: Open | G8: Participant stated that staff were “always careless about arrival times.” | H8: 04/11/2026 | I8: 04/11/2026 11:00 | L8: Complaint record extract; participant statement supplied verbatim.
A9: CAR-06 | B9: Incident | C9: 03/11/2026 | D9: P06 | E9: Rhonda Blake | F9: Closed | G9: Minor fall reported; immediate action and owner handoff completed. | H9: 03/11/2026 | I9: 03/11/2026 14:00 | J9: Immediate action completed. | K9: Owner handoff and closure note recorded. | L9: Incident record extract.

Sheet M15_Capstone_Invoice_Evidence
A1: M15 — Capstone Invoice Evidence
A2: FICTIONAL TRAINING DATA. Neutral evidence only. Do not treat evidence text as the classification.
A3: Evidence ID | B3: Participant ID | C3: Service Date | D3: Item Code | E3: Qty | F3: Delivery / Evidence Note
A4: CSD-2001 | B4: P03 | C4: 02/11/2026 | D4: FX-DL-WD | E4: 2 | F4: Service record shows one occurrence from 09:00–11:00; both invoice lines reference this same record.
A5: CSD-2004 | B5: P06 | C5: 04/11/2026 | D5: FX-DL-WE | E5: 3 | F5: Service record shows delivery from 17:00–20:00.
A6: CSD-2005 | B6: P08 | C6: 04/11/2026 | D6: FX-CA-WD | E6: 2 | F6: Service record shows delivery from 10:00–12:00.
A7: CSD-2006 | B7: P09 | C7: 04/11/2026 | D7: FX-SC-01 | E7: 1 | F7: Service record shows delivery from 09:00–10:00.
